Workbook

Sheet Misc Data + Calculations
A1: Date | B1: EWBC | C1: KRE | D1: Low | E1: Close | F1: Adj Close | G1: Volume
A2: 44739 | B2: 67.010002 | C2: 59.939999 | D2: 66.139999 | E2: 66.889999 | F2: 65.116997 | G2: 545000
A3: 44740 | B3: 67.330002 | C3: 59.919998 | D3: 66.419998 | E3: 67.019997 | F3: 65.243546 | G3: 1125900
A4: 44741 | B4: 67.220001 | C4: 59.18 | D4: 65.980003 | E4: 66.43 | F4: 64.669189 | G4: 966400
A5: 44742 | B5: 64.449997 | C5: 57.599998 | D5: 63.200001 | E5: 64.800003 | F5: 63.082401 | G5: 1171600
A6: 44743 | B6: 64.809998 | C6: 57.860001 | D6: 64.150002 | E6: 65.699997 | F6: 63.958534 | G6: 620800
A7: 44747 | B7: 63.880001 | C7: 58 | D7: 63.25 | E7: 66.419998 | F7: 64.659447 | G7: 680500
A8: 44748 | B8: 65.720001 | C8: 59.029999 | D8: 64.690002 | E8: 66.089996 | F8: 64.338203 | G8: 707000 | Y8: Loans | AB8: Deposits | AF8: 17.0% 17.4% 17.9% 18.5% 19.2%
A9: 44749 | B9: 66.470001 | C9: 59.27 | D9: 66.470001 | E9: 67.260002 | F9: 65.47718 | G9: 534000 | X9: CRE | Y9: 0.4 | AA9: Demand | AB9: 0.3
A10: 44750 | B10: 67.650002 | C10: 59.580002 | D10: 66.370003 | E10: 67.279999 | F10: 65.496658 | G10: 648100 | X10: C&I | Y10: 0.31 | AA10: Time | AB10: 0.3
A11: 44753 | B11: 66.370003 | C11: 58.73 | D11: 65.290001 | E11: 65.639999 | F11: 63.900131 | G11: 693600 | X11: Resi | Y11: 0.29 | AA11: Money Mkt | AB11: 0.21 | AF11: Q4 19 | AG11: 0.127
A12: 44754 | B12: 65.010002 | C12: 58.189999 | D12: 65 | E12: 66.050003 | F12: 64.299263 | G12: 567000 | AA12: Checking | AB12: 0.19 | AF12: Q1 20 | AG12: 0.127
A13: 44755 | B13: 65.540001 | C13: 58.16 | D13: 64.550003 | E13: 65.160004 | F13: 63.432854 | G13: 577200 | AF13: Q2 20 | AG13: 0.131
A14: 44756 | B14: 63.630001 | C14: 56.720001 | D14: 62.790001 | E14: 63.860001 | F14: 62.167309 | G14: 588600 | AF14: Q3 20 | AG14: 0.139
A15: 44757 | B15: 65.129997 | C15: 57.810001 | D15: 64.010002 | E15: 66.400002 | F15: 64.639984 | G15: 554000 | AF15: Q4 20 | AG15: 0.147
A16: 44760 | B16: 67.199997 | C16: 59.41 | D16: 67.080002 | E16: 67.379997 | F16: 65.594002 | G16: 956400 | AF16: Q1 21 | AG16: 0.155
A17: 44761 | B17: 68.550003 | C17: 59.75 | D17: 68.279999 | E17: 69.790001 | F17: 67.940125 | G17: 837100 | AF17: Q2 21 | AG17: 0.165
A18: 44762 | B18: 68.970001 | C18: 60.619999 | D18: 68.550003 | E18: 71.160004 | F18: 69.273811 | G18: 1150400 | AF18: Q3 21 | AG18: 0.168
A19: 44763 | B19: 71.169998 | C19: 61.48 | D19: 69.959999 | E19: 71.589996 | F19: 69.692406 | G19: 1214400 | AF19: Q4 21 | AG19: 0.17
A20: 44764 | B20: 71.93 | C20: 61.950001 | D20: 69.32 | E20: 69.849998 | F20: 67.998535 | G20: 652700 | AF20: Q1 22 | AG20: 0.172
A21: 44767 | B21: 70.879997 | C21: 61.560001 | D21: 70.510002 | E21: 72.089996 | F21: 70.179161 | G21: 727800 | AF21: Q2 22 | AG21: 0.17
A22: 44768 | B22: 71.160004 | C22: 61.849998 | D22: 69.370003 | E22: 69.389999 | F22: 67.550728 | G22: 606000 | AF22: Q3 22 | AG22: 0.174
A23: 44769 | B23: 69.650002 | C23: 61.900002 | D23: 69.489998 | E23: 70.790001 | F23: 68.913628 | G23: 618600 | AF23: Q4 22 | AG23: 0.179
A24: 44770 | B24: 70.470001 | C24: 62.810001 | D24: 68.959999 | E24: 70.459999 | F24: 68.592369 | G24: 603700 | AF24: Q1 23 | AG24: 0.185
A25: 44771 | B25: 70.099998 | C25: 62.919998 | D25: 70 | E25: 71.779999 | F25: 70.276337 | G25: 1010300 | AF25: Q2 23 | AG25: 0.192
A26: 44774 | B26: 71.059998 | C26: 63.389999 | D26: 70.410004 | E26: 71.440002 | F26: 69.943459 | G26: 906600
A27: 44775 | B27: 71.040001 | C27: 63.619999 | D27: 69.959999 | E27: 70.190002 | F27: 68.71965 | G27: 732400
A28: 44776 | B28: 70.849998 | C28: 63.540001 | D28: 70.260002 | E28: 70.699997 | F28: 69.218964 | G28: 658900 | AF28: New York | AG28: 0.22975
A29: 44777 | B29: 70.440002 | C29: 63.759998 | D29: 69.029999 | E29: 69.120003 | F29: 67.672066 | G29: 589600 | AF29: LA | AG29: 0.258
A30: 44778 | B30: 68.68 | C30: 63.25 | D30: 68.589996 | E30: 70.230003 | F30: 68.758812 | G30: 480200 | AF30: Chicago | AG30: 0.238
A31: 44781 | B31: 70.389999 | C31: 64.199997 | D31: 69.980003 | E31: 70.150002 | F31: 68.680481 | G31: 373100 | AF31: Houston | AG31: 0.252
A32: 44782 | B32: 70.260002 | C32: 64.029999 | D32: 69.25 | E32: 70.089996 | F32: 68.621735 | G32: 536700 | AF32: Phoenix | AG32: 0.261
A33: 44783 | B33: 71.529999 | C33: 64.989998 | D33: 71.209999 | E33: 73.900002 | F33: 72.351929 | G33: 827700 | AF33: Philly | AG33: 0.203
A34: 44784 | B34: 74.230003 | C34: 66.139999 | D34: 74.230003 | E34: 74.660004 | F34: 73.096008 | G34: 506000
A35: 44785 | B35: 75.199997 | C35: 67.040001 | D35: 74.75 | E35: 75.989998 | F35: 74.398148 | G35: 447300
A36: 44788 | B36: 75.419998 | C36: 66.93 | D36: 75.120003 | E36: 76.540001 | F36: 74.936623 | G36: 509200
A37: 44789 | B37: 76.080002 | C37: 67.559998 | D37: 76.080002 | E37: 77.57 | F37: 75.945053 | G37: 483100
A38: 44790 | B38: 76.389999 | C38: 67.720001 | D38: 75.980003 | E38: 76.470001 | F38: 74.868088 | G38: 509200
A39: 44791 | B39: 76.830002 | C39: 67.800003 | D39: 76.209999 | E39: 77.209999 | F39: 75.59259 | G39: 411700
A40: 44792 | B40: 76.720001 | C40: 67.550003 | D40: 75.839996 | E40: 76.339996 | F40: 74.740814 | G40: 802000
A41: 44795 | B41: 75.169998 | C41: 65.900002 | D41: 74.040001 | E41: 74.43 | F41: 72.870827 | G41: 739400
A42: 44796 | B42: 74.779999 | C42: 65.290001 | D42: 74.110001 | E42: 74.360001 | F42: 72.802292 | G42: 496400
A43: 44797 | B43: 74 | C43: 64.889999 | D43: 73.610001 | E43: 74.419998 | F43: 72.861031 | G43: 281800
A44: 44798 | B44: 74.519997 | C44: 64.699997 | D44: 74.519997 | E44: 76.169998 | F44: 74.574371 | G44: 478300
A45: 44799 | B45: 76.410004 | C45: 66.040001 | D45: 73.93 | E45: 73.940002 | F45: 72.39109 | G45: 515600
... A58: 44819 | B58: 73.339996 | C58: 62.630001 | D58: 73.339996 | E58: 74.199997 | F58: 72.645638 | G58: 632700
A59: 44820 | B59: 72.779999 | C59: 62.790001 | D59: 71.400002 | E59: 72.669998 | F59: 71.14769 | G59: 2528600 | AO59: 2023 | AP59: 2024 | AQ59: 2025 | AR59: 2026 | AS59: 2027 | AT59: 2028 | AU59: 2029 | AV59: 2030
A60: 44823 | B60: 71.449997 | C60: 61.84 | D60: 71.449997 | E60: 74.190002 | F60: 72.635857 | G60: 667200 | AO60: 92 | AP60: 58 | AQ60: 47 | AR60: 30 | AS60: 37 | AT60: 24 | AU60: 31 | AV60: 18
A61: 44824 | B61: 73.690002 | C61: 63.27 | D61: 72.900002 | E61: 73.589996 | F61: 72.048409 | G61: 509000 | AO61: =SUM(AO60:AV60) -> 337
A62: 44825 | B62: 73.720001 | C62: 63.720001 | D62: 72.470001 | E62: 72.470001 | F62: 70.951889 | G62: 484400 | AO62: 2023 | AP62: 2024 | AQ62: 2025 | AR62: 2026 | AS62: 2027 | AT62: 2028 | AU62: 2029 | AV62: 2030
A63: 44826 | B63: 72.629997 | C63: 62.91 | D63: 69.529999 | E63: 69.730003 | F63: 68.269287 | G63: 760500 | AO63: =AO60/$AO$61 -> 0.27299703 | AP63: =AP60/$AO$61 -> 0.17210682 | AQ63: =AQ60/$AO$61 -> 0.13946588 | AR63: =AR60/$AO$61 -> 0.089020772 | AS63: =AS60/$AO$61 -> 0.10979228 | AT63: =AT60/$AO$61 -> 0.071216617 | AU63: =AU60/$AO$61 -> 0.091988131 | AV63: =AV60/$AO$61 -> 0.053412463
A64: 44827 | B64: 68.709999 | C64: 60.549999 | D64: 66.300003 | E64: 67.620003 | F64: 66.203484 | G64: 844700 | AP64: =SUM(AO63:AP63) -> 0.44510386
A65: 44830 | B65: 67.160004 | C65: 59.799999 | D65: 66.690002 | E65: 67.059998 | F65: 65.655205 | G65: 774100
A66: 44831 | B66: 67.540001 | C66: 60.209999 | D66: 65.769997 | E66: 66.839996 | F66: 65.439819 | G66: 707100
A67: 44832 | B67: 67.300003 | C67: 59.23 | D67: 67 | E67: 68.339996 | F67: 66.908394 | G67: 581900
A68: 44833 | B68: 67.25 | C68: 59.299999 | D68: 66.110001 | E68: 67.610001 | F68: 66.193695 | G68: 598700
A69: 44834 | B69: 67.809998 | C69: 59.09 | D69: 67 | E69: 67.139999 | F69: 65.733543 | G69: 883100
A70: 44837 | B70: 68.050003 | C70: 59.540001 | D70: 66.809998 | E70: 69.269997 | F70: 67.818909 | G70: 726200
A71: 44838 | B71: 70.720001 | C71: 61.009998 | D71: 70.559998 | E71: 73.860001 | F71: 72.312767 | G71: 743200
A72: 44839 | B72: 72.18 | C72: 61.950001 | D72: 71.010002 | E72: 73.550003 | F72: 72.009262 | G72: 666200
A73: 44840 | B73: 72.830002 | C73: 61.849998 | D73: 72.629997 | E73: 73.050003 | F73: 71.51973 | G73: 492600
A74: 44841 | B74: 72.269997 | C74: 61.240002 | D74: 70.480003 | E74: 71.059998 | F74: 69.571419 | G74: 593400
A75: 44844 | B75: 71.660004 | C75: 60.75 | D75: 70.199997 | E75: 70.709999 | F75: 69.228745 | G75: 614600
A76: 44845 | B76: 70.330002 | C76: 59.849998 | D76: 69.309998 | E76: 69.860001 | F76: 68.396561 | G76: 725200
... A81: 44852 | B81: 73.870003 | C81: 63.919998 | D81: 72.099998 | E81: 73.029999 | F81: 71.500153 | G81: 714200
A82: 44853 | B82: 72.32 | C82: 62.529999 | D82: 70.300003 | E82: 70.989998 | F82: 69.502892 | G82: 1047700 | AF82: CRE ALL Impact Build
A83: 44854 | B83: 68.050003 | C83: 61.619999 | D83: 63.200001 | E83: 64.389999 | F83: 63.041142 | G83: 2117300 | AF83: Current CRE NCO rate (H1) | AG83: =2018/AG85 -> 0.00010131217
A84: 44855 | B84: 63.84 | C84: 59.82 | D84: 63 | E84: 66.699997 | F84: 65.302757 | G84: 1294800 | AF84: Provision for CRE losses in H2 23 (estimated) | AG84: 22097
A85: 44858 | B85: 67.029999 | C85: 60.98 | D85: 66.790001 | E85: 67.360001 | F85: 65.948929 | G85: 1069500 | AF85: CRE Loans | AG85: 19918633
A86: 44859 | B86: 66.82 | C86: 61.189999 | D86: 66.400002 | E86: 68.459999 | F86: 67.025887 | G86: 601900 | AF86: Implied NCO rate | AG86: =AG84/AG85 -> 0.0011093633
A87: 44860 | B87: 68.629997 | C87: 62.560001 | D87: 68.07 | E87: 69.860001 | F87: 68.396561 | G87: 900900
A88: 44861 | B88: 70.800003 | C88: 62.98 | D88: 69.57 | E88: 69.889999 | F88: 68.425926 | G88: 811900 | AP88: 45057 | AQ88: EWBC | AR88: Alvarez Manuel Pham | AS88: Dir | AT88: P - Purchase | AU88: 43.6 | AV88: 1250 | AW88: 4445 | AX88: 0.39 | AY88: 54505
A89: 44862 | B89: 70.650002 | C89: 62.639999 | D89: 69.800003 | E89: 71.639999 | F89: 70.139267 | G89: 804400 | AO89: 45062.523
A90: 44865 | B90: 70.540001 | C90: 63.52 | D90: 70.540001 | E90: 71.57 | F90: 70.464172 | G90: 827100 | AO90: M | AP90: 45056.605 | AQ90: 45054 | AR90: EWBC | AS90: Deskus Archana | AT90: Dir | AU90: P - Purchase | AV90: 44.44 | AW90: 1000 | AX90: 9193 | AY90: 0.12 | AZ90: 44440
A91: 44866 | B91: 72.550003 | C91: 64.400002 | D91: 71.440002 | E91: 72.019997 | F91: 70.907211 | G91: 590000 | AP91: 45056.535 | AQ91: 45054 | AR91: EWBC | AS91: Alvarez Manuel Pham | AT91: Dir | AU91: P - Purchase | AV91: 45.19 | AW91: 500 | AX91: 3195 | AY91: 0.19 | AZ91: 22595
A92: 44867 | B92: 71.860001 | C92: 63.720001 | D92: 67.730003 | E92: 68 | F92: 66.949333 | G92: 1543900 | AP92: 45055.637 | AQ92: 45055 | AR92: EWBC | AS92: Kay Sabrina | AT92: Dir | AU92: P - Purchase | AV92: 43.88 | AW92: 6840 | AX92: 8846 | AY92: 3.41 | AZ92: 300105
A93: 44868 | B93: 67.419998 | C93: 61.82 | D93: 66.57 | E93: 68 | F93: 66.949333 | G93: 1063100 | AP93: 45054.592 | AQ93: 45054 | AR93: EWBC | AS93: Campbell Molly | AT93: Dir | AU93: P - Purchase | AV93: 45.15 | AW93: 650 | AX93: 13843 | AY93: 0.05 | AZ93: 29348
A94: 44869 | B94: 69.410004 | C94: 62.700001 | D94: 68.809998 | E94: 70.019997 | F94: 68.938118 | G94: 984800 | AP94: 45054.557 | AQ94: 45051 | AR94: EWBC | AS94: Sussman Lester | AT94: Dir | AU94: P - Purchase | AV94: 44.19 | AW94: 1000 | AX94: 20577 | AY94: 0.05 | AZ94: 44194
A95: 44872 | B95: 70.629997 | C95: 63.709999 | D95: 68.970001 | E95: 69.75 | F95: 68.672287 | G95: 671300 | AP95: 45054.467 | AQ95: 45051 | AR95: EWBC | AS95: Ng Dominic | AT95: CEO | AU95: P - Purchase | AV95: 43.94 | AW95: 5700 | AX95: 902452 | AY95: 0.01 | AZ95: 250437
A96: 44873 | B96: 69.57 | C96: 63.779999 | D96: 68.790001 | E96: 70.150002 | F96: 69.066109 | G96: 947100 | AP96: 45050.753 | AQ96: 45050 | AR96: EWBC | AS96: Shi Parker | AT96: COO | AU96: P - Purchase | AV96: 41.94 | AW96: 4780 | AX96: 4780 | AY96: New | AZ96: 200473
A97: 44874 | B97: 69.43 | C97: 63.029999 | D97: 68.550003 | E97: 68.940002 | F97: 67.874809 | G97: 900000 | AP97: 45050.752 | AQ97: 45050 | AR97: EWBC | AS97: Ng Dominic | AT97: CEO | AU97: P - Purchase | AV97: 42.09 | AW97: 11900 | AX97: 896752 | AY97: 0.01 | AZ97: 500889
A98: 44875 | B98: 71.269997 | C98: 64.370003 | D98: 71.269997 | E98: 73.919998 | F98: 72.777855 | G98: 1164400 | AP98: 45050.591 | AQ98: 45050 | AR98: EWBC | AS98: Oh Irene H | AT98: CFO | AU98: P - Purchase | AV98: 43 | AW98: 1000 | AX98: 128215 | AY98: 0.01 | AZ98: 43000
A99: 44876 | B99: 73.959999 | C99: 65.489998 | D99: 73.57 | E99: 74.07 | F99: 72.925545 | G99: 1035400 | AP99: 45050.59 | AQ99: 45050 | AR99: EWBC | AS99: Teo Gary | AT99: EVP | AU99: P - Purchase | AV99: 43 | AW99: 3450 | AX99: 14855 | AY99: 0.3 | AZ99: 148350
A100: 44879 | B100: 73.470001 | C100: 64.82 | D100: 71.760002 | E100: 71.800003 | F100: 70.69062 | G100: 905500 | AP100: 44998.662 | AQ100: 44998 | AR100: EWBC | AS100: Oh Irene H | AT100: CFO | AU100: P - Purchase | AV100: 49.51 | AW100: 10000 | AX100: 127215 | AY100: 0.09 | AZ100: 495130
A101: 44880 | B101: 72.82 | C101: 64.940002 | D101: 71.349998 | E101: 71.660004 | F101: 70.55278 | G101: 1531300
A102: 44881 | B102: 71.360001 | C102: 64.389999 | D102: 68.610001 | E102: 68.760002 | F102: 67.697594 | G102: 1014200
A103: 44882 | B103: 68.07 | C103: 62.740002 | D103: 66.309998 | E103: 67.339996 | F103: 66.299522 | G103: 1412700
A104: 44883 | B104: 68.730003 | C104: 63.240002 | D104: 66.25 | E104: 67.230003 | F104: 66.191231 | G104: 952300 | AO104: X
A105: 44886 | B105: 67.489998 | C105: 62.880001 | D105: 67.029999 | E105: 68 | F105: 66.949333 | G105: 662000 | AO105: Filing Date
A106: 44887 | B106: 68.410004 | C106: 63.68 | D106: 67.900002 | E106: 69.550003 | F106: 68.475388 | G106: 638300 | AO106: Trade Date
A107: 44888 | B107: 69.25 | C107: 63.939999 | D107: 68.82 | E107: 69.160004 | F107: 68.091415 | G107: 477800 | AO107: Ticker
A108: 44890 | B108: 69.739998 | C108: 64.160004 | D108: 69.199997 | E108: 69.730003 | F108: 68.652603 | G108: 204700 | AO108: Insider Name
A109: 44893 | B109: 69.050003 | C109: 63.919998 | D109: 67.089996 | E109: 67.32 | F109: 66.279839 | G109: 834500 | AO109: Title
A110: 44894 | B110: 67.540001 | C110: 62.98 | D110: 66.870003 | E110: 68.139999 | F110: 67.087166 | G110: 722900 | AO110: Trade Type
A111: 44895 | B111: 68.059998 | C111: 63.34 | D111: 66.769997 | E111: 70.209999 | F111: 69.125183 | G111: 1156700 | AO111: Price
A112: 44896 | B112: 70.650002 | C112: 64.849998 | D112: 68.529999 | E112: 69.220001 | F112: 68.150482 | G112: 620900 | AO112: Qty
A113: 44897 | B113: 68.309998 | C113: 63.599998 | D113: 68.029999 | E113: 68.82 | F113: 67.75666 | G113: 529900 | AO113: Owned
A114: 44900 | B114: 68.230003 | C114: 63.509998 | D114: 62.91 | E114: 63.959999 | F114: 62.971752 | G114: 1450600 | AO114: ?Own
A115: 44901 | B115: 64.029999 | C115: 60.73 | D115: 63.52 | E115: 64.970001 | F115: 63.966148 | G115: 1657300 | AO115: Value
... A119: 44907 | B119: 65.900002 | C119: 60.09 | D119: 65.099998 | E119: 67.260002 | F119: 66.220764 | G119: 724900 | AO119: 6m
...

Sheet Net Income Build
A3: x | B3: East West Bancorp Net Income Build ($m) | C3: 2009 | D3: 2010 | E3: 2011 | F3: 2012 | G3: 2013 | H3: 2014 | I3: 2015 | J3: 2016 | K3: 2017 | L3: 2018 | M3: 2019 | N3: 2020 | O3: 2021 | P3: 2022 | Q3: 2023 | R3: 2024 | S3: 2025 | T3: 2026 | U3: 2027 | V3: 2028 | W3: 2029 | X3: 2030 | Y3: 2031 | Z3: 2032
B4: Average FFR | C4: 0.0016 | D4: 0.0018 | E4: 0.001 | F4: 0.0014 | G4: 0.0011 | H4: 0.0009 | I4: 0.0013 | J4: 0.004 | K4: 0.01 | L4: 0.0183 | M4: 0.0216 | N4: 0.0038 | O4: 0.0008 | P4: 0.0168 | Q4: 0.0508 | R4: 0.0488 | S4: 0.0418 | T4: 0.0338 | U4: 0.025
B5: Cash and Cash with Banks | C5: =CW44 -> 881282 | D5: =CT44 -> 828039 | E5: =CO44 -> 1018490 | F5: =CL44 -> 1457153 | G5: =CI44 -> 1184709 | H5: =CD43 -> 1469200 | I5: =CA43 -> 1851604 | J5: =BX43 -> 1893064 | K5: =BS43 -> 2242256 | L5: =BP43 -> 2609463 | M5: =BM43 -> 3050954 | N5: =BE41 -> 4236430 | O5: =BB41 -> 6071896 | P5: =AY41 -> 3127234 | Q5: =Q$17*Q9/Q$21 -> 4449546.8 | R5: =R$17*R9/R$21 -> 3877362.9 | S5: =S$17*S9/S$21 -> 3758059.4 | T5: =T$17*T9/T$21 -> 3945962.4 | U5: =U$17*U9/U$21 -> 4044611.4
B6: Growth | D6: =D5/C5-1 -> -0.060415395 | E6: =E5/D5-1 -> 0.23000245 | F6: =F5/E5-1 -> 0.43069937 | G6: =G5/F5-1 -> -0.18697007 | H6: =H5/G5-1 -> 0.24013576 | I6: =I5/H5-1 -> 0.26028042 | J6: =J5/I5-1 -> 0.022391397 | K6: =K5/J5-1 -> 0.18445863 | ... U6: =U5/T5-1 -> 0.025
B7: Yield | C7: =CY44 -> 0.0103 | D7: =CV44 -> 0.0116 | E7: =CQ44 -> 0.0222 | F7: =CN44 -> 0.0153 | G7: =CK44 -> 0.0146 | H7: =CF43 -> 0.0158 | I7: =CC43 -> 0.0097 | J7: =BZ43 -> 0.0078 | K7: =BU43 -> 0.0149 | L7: =BR43 -> 0.021 | M7: =BO43 -> 0.0219 | N7: =BH41 -> 0.0059 | O7: =BD41 -> 0.0026 | P7: =BA41 -> 0.0131 | Q7: ='Misc Data + Calculations'!AY573 -> 0.0466 | R7: ='Misc Data + Calculations'!AZ573 -> 0.05 | S7: ='Misc Data + Calculations'!BA573 -> 0.044015748 | T7: ='Misc Data + Calculations'!BB573 -> 0.036457306 | U7: ='Misc Data + Calculations'!BC573 -> 0.029322838
B8: Delta to FFR | C8: =C7-C$4 -> 0.0087 | D8: =D7-D$4 -> 0.0098 | E8: =E7-E$4 -> 0.0212 | F8: =F7-F$4 -> 0.0139 | G8: =G7-G$4 -> 0.0135 | H8: =H7-H$4 -> 0.0149 | I8: =I7-I$4 -> 0.0084 | J8: =J7-J$4 -> 0.0038 | ... U8: =U7-U$4 -> 0.004322838
B9: % of IEA | C9: =C5/(SUM(C$5,C$11,C$17,C$23)) -> 0.068259223 | D9: =D5/(SUM(D$5,D$11,D$17,D$23)) -> 0.046714527 | E9: =E5/(SUM(E$5,E$11,E$17,E$23)) -> 0.05251734 | F9: =F5/(SUM(F$5,F$11,F$17,F$23)) -> 0.073440844 | G9: =G5/(SUM(G$5,G$11,G$17,G$23)) -> 0.054275592 | H9: =H5/(SUM(H$5,H$11,H$17,H$23)) -> 0.056948875 | I9: =I5/(SUM(I$5,I$11,I$17,I$23)) -> 0.065218952 | J9: =J5/(SUM(J$5,J$11,J$17,J$23)) -> 0.06048751 | ... P9: =P5/(SUM(P$5,P$11,P$17,P$23)) -> 0.05272776 | Q9: 0.07 | R9: 0.065 | S9: 0.06 | T9: 0.06 | U9: 0.06
B10: Cash Interest Earned (+) | C10: =C5*C7 -> 9077.2046 | D10: =D5*D7 -> 9605.2524 | E10: =E5*E7 -> 22610.478 | F10: =F5*F7 -> 22294.441 | G10: =G5*G7 -> 17296.751 | H10: =H5*H7 -> 23213.36 | I10: =I5*I7 -> 17960.559 | J10: =J5*J7 -> 14765.899 | ... U10: =U5*U7 -> 118599.49
B11: Repos | C11: =CW46 -> 89883 | D11: =CT46 -> 529817 | E11: =CO46 -> 1023043 | F11: =CL46 -> 1267284 | G11: =CI46 -> 1503014 | H11: =CD45 -> 1340411 | I11: =CA45 -> 1337274 | J11: =BX45 -> 1708470 | K11: =BS45 -> 1438767 | L11: =BP45 -> 1020822 | M11: =BM45 -> 969384 | N11: =BE44 -> 1101434 | O11: =BB44 -> 2107157 | P11: =AY44 -> 1398080 | Q11: =Q$17*Q15/Q$21 -> 635649.54 | R11: =R$17*R15/R$21 -> 596517.37 | S11: =S$17*S15/S$21 -> 2505372.9 | T11: =T$17*T15/T$21 -> 2630641.6 | U11: =U$17*U15/U$21 -> 2696407.6
B12: Growth | D12: =D11/C11-1 -> 4.8945184 | E12: =E11/D11-1 -> 0.93093653 | F12: =F11/E11-1 -> 0.23873972 | G12: =G11/F11-1 -> 0.18601198 | H12: =H11/G11-1 -> -0.10818462 | I12: =I11/H11-1 -> -0.002340327 | J12: =J11/I11-1 -> 0.27757662 | K12: =K11/J11-1 -> -0.1578623 | ... U12: =U11/T11-1 -> 0.025
B13: Yield | C13: =CY46 -> 0.0876 | D13: =CV46 -> 0.0264 | E13: =CQ46 -> 0.0188 | F13: =CN46 -> 0.0161 | G13: =CK46 -> 0.0141 | H13: =CF45 -> 0.0152 | I13: =CC45 -> 0.0148 | J13: =BZ45 -> 0.0179 | K13: =BU45 -> 0.0223 | L13: =BR45 -> 0.0287 | M13: =BO45 -> 0.0287 | N13: =BH44 -> 0.0194 | O13: =BD44 -> 0.0153 | P13: =BA44 -> 0.0213 | Q13: ='Misc Data + Calculations'!AY575 -> 0.0248 | R13: ='Misc Data + Calculations'!AZ575 -> 0.0275 | S13: ='Misc Data + Calculations'!BA575 -> 0.025305774 | T13: ='Misc Data + Calculations'!BB575 -> 0.022408747 | U13: ='Misc Data + Calculations'!BC575 -> 0.019485245
B14: Delta to FFR | C14: =C13-C$4 -> 0.086 | D14: =D13-D$4 -> 0.0246 | E14: =E13-E$4 -> 0.0178 | F14: =F13-F$4 -> 0.0147 | G14: =G13-G$4 -> 0.013 | H14: =H13-H$4 -> 0.0143 | I14: =I13-I$4 -> 0.0135 | J14: =J13-J$4 -> 0.0139 | ... U14: =U13-U$4 -> -0.0055147545
B15: % of IEA | C15: =C11/(SUM(C$5,C$11,C$17,C$23)) -> 0.0069618394 | D15: =D11/(SUM(D$5,D$11,D$17,D$23)) -> 0.029890078 | E15: =E11/(SUM(E$5,E$11,E$17,E$23)) -> 0.052752111 | F15: =F11/(SUM(F$5,F$11,F$17,F$23)) -> 0.063871403 | G15: =G11/(SUM(G$5,G$11,G$17,G$23)) -> 0.068858238 | H15: =H11/(SUM(H$5,H$11,H$17,H$23)) -> 0.051956778 | I15: =I11/(SUM(I$5,I$11,I$17,I$23)) -> 0.047102733 | J15: =J11/(SUM(J$5,J$11,J$17,J$23)) -> 0.054589331 | ... P15: =P11/(SUM(P$5,P$11,P$17,P$23)) -> 0.023572789 | Q15: 0.01 | R15: 0.01 | S15: 0.04 | T15: 0.04 | U15: 0.04 | AB15: 0.079 | AC15: 0.5 | AD15: =AC15+1 -> 1.5 | AE15: =AD15+1 -> 2.5 | AF15: =AE15+1 -> 3.5 | AG15: =AF15+1 -> 4.5
B16: Repo Interest Earned (+) | C16: =C11*C13 -> 7873.7508 | D16: =D11*D13 -> 13987.169 | E16: =E11*E13 -> 19233.208 | F16: =F11*F13 -> 20403.272 | G16: =G11*G13 -> 21192.497 | H16: =H11*H13 -> 20374.247 | I16: =I11*I13 -> 19791.655 | J16: =J11*J13 -> 30581.613 | ... U16: =U11*U13 -> 52540.164 | AB16: =SUM(P11,P17,P23) -> 56181828 | AC16: =SUM(Q11,Q17,Q23) -> 59115407 | AD16: =SUM(R11,R17,R23) -> 55774374 | AE16: =SUM(S11,S17,S23) -> 58876264 | AF16: =SUM(T11,T17,T23) -> 61820077 | AG16: =SUM(U11,U17,U23) -> 63365579
B17: Loans | C17: =CW56 -> 9232854 | D17: =CT56 -> 13708914 | E17: =CO56 -> 14037426 | F17: =CL56 -> 14469438 | G17: =CI56 -> 16275997 | H17: =CD52 -> 20351818 | I17: =CA52 -> 22276589 | J17: =BX52 -> 24264895 | K17: =BS52 -> 27252756 | L17: =BP52 -> 30230014 | M17: =BM52 -> 33373136 | N17: =BE52 -> 36799017 | O17: =BB52 -> 39716697 | P17: =AY52 -> 45319458 | Q17: =P17*(1+Q18) -> 48945015 | R17: =Q17*(1+R18) -> 47721389 | S17: =R17*(1+S18) -> 50107459 | T17: =S17*(1+T18) -> 52612832 | U17: =T17*(1+U18) -> 53928152 | AB17: =SUM(P31,P42,P48) -> 55107002 | AC17: =SUM(Q31,Q42,Q48) -> 59088426 | AD17: =SUM(R31,R42,R48) -> 56020761 | AE17: =SUM(S31,S42,S48) -> 57506367 | AF17: =SUM(T31,T42,T48) -> 59395540 | AG17: =SUM(U31,U42,U48) -> 60842018
B18: Growth | D18: =D17/C17-1 -> 0.48479701 | E18: =E17/D17-1 -> 0.023963386 | F18: =F17/E17-1 -> 0.030775728 | G18: =G17/F17-1 -> 0.12485343 | H18: =H17/G17-1 -> 0.25041913 | I18: =I17/H17-1 -> 0.094574893 | J18: =J17/I17-1 -> 0.089255406 | K18: =K17/J17-1 -> 0.12313513 | ... P18: =P17/O17-1 -> 0.14106815 | Q18: 0.08 | R18: -0.025 | S18: 0.05 | T18: 0.05 | U18: 0.025 | AB18: =AB16-AB17 -> 1074826 | AC18: =AC16-AC17 -> 26981.379 | AD18: =AD16-AD17 -> -246387.61 | AE18: =AE16-AE17 -> 1369896.9 | AF18: =AF16-AF17 -> 2424537.2 | AG18: =AG16-AG17 -> 2523561
B19: Yield | C19: =CY56 -> 0.063594962 | D19: =CV56 -> 0.072842313 | E19: =CQ56 -> 0.067376882 | F19: =CN56 -> 0.065346698 | G19: =CK56 -> 0.060174132 | H19: =CF52 -> 0.052 | I19: =CC52 -> 0.0435 | J19: =BZ52 -> 0.0427 | K19: =BU52 -> 0.044 | L19: =BR52 -> 0.0497 | M19: =BO52 -> 0.0515 | N19: =BH52 -> 0.0398 | O19: =BD52 -> 0.0359 | P19: =BA52 -> 0.0452 | Q19: ='Misc Data + Calculations'!AY577 -> 0.0633 | R19: ='Misc Data + Calculations'!AZ577 -> 0.065 | S19: ='Misc Data + Calculations'!BA577 -> 0.062735236 | T19: ='Misc Data + Calculations'!BB577 -> 0.058917129 | U19: ='Misc Data + Calculations'!BC577 -> 0.054625199 | AC19: =AC18-AB18 -> -1047844.6 | AD19: =AD18-AC18 -> -273368.99 | AE19: =AE18-AD18 -> 1616284.5 | AF19: =AF18-AE18 -> 1054640.3 | AG19: =AG18-AF18 -> 99023.795
B20: Delta to FFR | C20: =C19-C$4 -> 0.061994962 | D20: =D19-D$4 -> 0.071042313 | E20: =E19-E$4 -> 0.066376882 | F20: =F19-F$4 -> 0.063946698 | G20: =G19-G$4 -> 0.059074132 | H20: =H19-H$4 -> 0.0511 | I20: =I19-I$4 -> 0.0422 | J20: =J19-J$4 -> 0.0387 | ... U20: =U19-U$4 -> 0.029625199 | AC20: =AC19/(AC15)^AB15 -> -1106823.2 | AD20: =AD19/(AD15)^AC15 -> -223204.84 | AE20: =AE19/(AE15)^AD15 -> 408891.23 | AF20: =AF19/(AF15)^AE15 -> 46018.689 | AG20: =AG19/(AG15)^AF15 -> 512.26628 | AH20: =SUM(AC20:AG20) -> -874605.87
B21: % of IEA | C21: =C17/(SUM(C$5,C$11,C$17,C$23)) -> 0.71512574 | D21: =D17/(SUM(D$5,D$11,D$17,D$23)) -> 0.77340008 | E21: =E17/(SUM(E$5,E$11,E$17,E$23)) -> 0.72382476 | F21: =F17/(SUM(F$5,F$11,F$17,F$23)) -> 0.72926298 | G21: =G17/(SUM(G$5,G$11,G$17,G$23)) -> 0.74565937 | H21: =H17/(SUM(H$5,H$11,H$17,H$23)) -> 0.78887363 | I21: =I17/(SUM(I$5,I$11,I$17,I$23)) -> 0.78464714 | J21: =J17/(SUM(J$5,J$11,J$17,J$23)) -> 0.77531615 | ... P21: =P17/(SUM(P$5,P$11,P$17,P$23)) -> 0.76412367 | Q21: 0.77 | R21: 0.8 | S21: 0.8 | T21: 0.8 | U21: 0.8
B22: Loan Interest Earned (+) | C22: =C17*C19 -> 587163 | D22: =D17*D19 -> 998589 | E22: =E17*E19 -> 945798 | F22: =F17*F19 -> 945530 | G22: =G17*G19 -> 979394 | H22: =H17*H19 -> 1058294.5 | I22: =I17*I19 -> 969031.62 | J22: =J17*J19 -> 1036111 | ... U22: =U17*U19 -> 2945836.1
B23: Securities | C23: =CW51 -> 2706793 | D23: =CT51 -> 2658744 | E23: =CO51 -> 3314445 | F23: =CL51 -> 2647305 | G23: =CI51 -> 2863937 | H23: =CD50 -> 2637149 | I23: =CA50 -> 2925115 | J23: =BX50 -> 3430346 | K23: =BS50 -> 3100286 | L23: =BP50 -> 2846843 | M23: =BM50 -> 2927330 | N23: =BE50 -> 4102828 | O23: =BB50 -> 8360638 | P23: =AY50 -> 9464290 | Q23: =Q$17*Q27/Q$21 -> 9534743.1 | R23: =R$17*R27/R$21 -> 7456467.1 | S23: =S$17*S27/S$21 -> 6263432.3 | T23: =T$17*T27/T$21 -> 6576604 | U23: =U$17*U27/U$21 -> 6741019.1
B24: Growth | D24: =D23/C23-1 -> -0.017751265 | E24: =E23/D23-1 -> 0.24662058 | F24: =F23/E23-1 -> -0.20128257 | G24: =G23/F23-1 -> 0.081831145 | H24: =H23/G23-1 -> -0.079187496 | I24: =I23/H23-1 -> 0.10919595 | J24: =J23/I23-1 -> 0.17272176 | K24: =K23/J23-1 -> -0.096217699 | ... U24: =U23/T23-1 -> 0.025
B25: Yield | C25: =CY51 -> 0.043972701 | D25: =CV51 -> 0.02760702 | E25: =CQ51 -> 0.028016455 | F25: =CN51 -> 0.02374377 | G25: =CK51 -> 0.017708141 | H25: =CF50 -> 0.019322382 | I25: =CC50 -> 0.016222268 | J25: =BZ50 -> 0.016565676 | K25: =BU50 -> 0.019738179 | L25: =BR50 -> 0.022501065 | M25: =BO50 -> 0.024017108 | N25: 0.0205 | O25: =BD50 -> 0.017470437 | P25: =BA50 -> 0.02134867 | Q25: ='Misc Data + Calculations'!AY579 -> 0.03 | R25: ='Misc Data + Calculations'!AZ579 -> 0.0325 | S25: ='Misc Data + Calculations'!BA579 -> 0.029906824 | T25: ='Misc Data + Calculations'!BB579 -> 0.026483065 | U25: ='Misc Data + Calculations'!BC579 -> 0.023028017
B26: Delta to FFR | C26: =C25-C$4 -> 0.042372701 | D26: =D25-D$4 -> 0.02580702 | E26: =E25-E$4 -> 0.027016455 | F26: =F25-F$4 -> 0.02234377 | G26: =G25-G$4 -> 0.016608141 | H26: =H25-H$4 -> 0.018422382 | I26: =I25-I$4 -> 0.014922268 | J26: =J25-J$4 -> 0.012565676 | ... U26: =U25-U$4 -> -0.0019719826
B27: % of IEA | C27: =C23/(SUM(C$5,C$11,C$17,C$23)) -> 0.2096532 | D27: =D23/(SUM(D$5,D$11,D$17,D$23)) -> 0.14999531 | E27: =E23/(SUM(E$5,E$11,E$17,E$23)) -> 0.17090579 | F27: =F23/(SUM(F$5,F$11,F$17,F$23)) -> 0.13342478 | G27: =G23/(SUM(G$5,G$11,G$17,G$23)) -> 0.1312068 | H27: =H23/(SUM(H$5,H$11,H$17,H$23)) -> 0.10222071 | I27: =I23/(SUM(I$5,I$11,I$17,I$23)) -> 0.10303117 | J27: =J23/(SUM(J$5,J$11,J$17,J$23)) -> 0.10960701 | ... P27: =P23/(SUM(P$5,P$11,P$17,P$23)) -> 0.15957578 | Q27: 0.15 | R27: 0.125 | S27: 0.1 | T27: 0.1 | U27: 0.1
B28: Securities Interest Earned (+) | C28: =C23*C25 -> 119025 | D28: =D23*D25 -> 73400 | E28: =E23*E25 -> 92859 | F28: =F23*F25 -> 62857 | G28: =G23*G25 -> 50715 | H28: =H23*H25 -> 50956 | I28: =I23*I25 -> 47452 | J28: =J23*J25 -> 56826 | ... U28: =U23*U25 -> 155232.3
A29: x | B29: Total Interest Income | C29: =SUM(C28,C22,C16,C10) -> 723138.96 | D29: =SUM(D28,D22,D16,D10) -> 1095581.4 | E29: =SUM(E28,E22,E16,E10) -> 1080500.7 | F29: =SUM(F28,F22,F16,F10) -> 1051084.7 | G29: =SUM(G28,G22,G16,G10) -> 1068598.2 | H29: =SUM(H28,H22,H16,H10) -> 1152838.1 | I29: =SUM(I28,I22,I16,I10) -> 1054235.8 | J29: =SUM(J28,J22,J16,J10) -> 1138284.5 | ... U29: =SUM(U28,U22,U16,U10) -> 3272208
B30: LTD Ratio | C30: =C17/C31 -> 0.97824942 | D30: =D17/D31 -> 0.92063628 | E30: =E17/E31 -> 0.8335435 | F30: =F17/F31 -> 0.82458099 | G30: =G17/G31 -> 0.83916781 | H30: =H17/H31 -> 0.88717718 | I30: =I17/I31 -> 0.86492215 | J30: =J17/J31 -> 0.85132897 | ... P30: =P17/P31 -> 0.83461896 | Q30: 0.9 | R30: 0.9 | S30: 0.9 | T30: 0.9 | U30: 0.9
B31: Deposits | C31: =C33+C35 -> 9438139 | D31: =D33+D35 -> 14890695 | E31: =E33+E35 -> 16840664 | F31: =F33+F35 -> 17547625 | G31: =G33+G35 -> 19395402 | H31: =H33+H35 -> 22939970 | I31: =I33+I35 -> 25755600 | J31: =J33+J35 -> 28502372 | ... P31: =P33+P35 -> 54299579 | Q31: =Q17/Q30 -> 54383350 | R31: =R17/R30 -> 53023766 | S31: =S17/S30 -> 55674954 | T31: =T17/T30 -> 58458702 | U31: =U17/U30 -> 59920169
B32: Deposit Growth | D32: =D31/C31-1 -> 0.57771516 | E32: =E31/D31-1 -> 0.13095218 | F32: =F31/E31-1 -> 0.041979402 | G32: =G31/F31-1 -> 0.10530069 | H32: =H31/G31-1 -> 0.18275301 | I32: =I31/H31-1 -> 0.12273904 | J32: =J31/I31-1 -> 0.10664756 | K32: =K31/J31-1 -> 0.08109511 | ... U32: =U31/T31-1 -> 0.025
B33: NIB Deposits | C33: =CW82 -> 1459871 | D33: =CT82 -> 2418816 | E33: =CO82 -> 3087777 | F33: =CL82 -> 3902534 | G33: =CI82 -> 5179687 | H33: =CD75 -> 6834871 | I33: =CA75 -> 7928460 | J33: =BX75 -> 9371481 | K33: =BS75 -> 10627718 | L33: =BP75 -> 11089537 | M33: =BM75 -> 10502618 | N33: =BE84 -> 13823152 | O33: =BB84 -> 21271410 | P33: =AY84 -> 22784258 | Q33: =Q34*Q31 -> 16315005 | R33: =R34*R31 -> 18558318 | S33: =S34*S31 -> 20878108 | T33: =T34*T31 -> 21922013 | U33: =U34*U31 -> 23968068
B34: NIB % of Deposits | C34: =C33/SUM(C33,C35) -> 0.15467784 | D34: =D33/SUM(D33,D35) -> 0.16243809 | E34: =E33/SUM(E33,E35) -> 0.18335245 | F34: =F33/SUM(F33,F35) -> 0.22239671 | G34: =G33/SUM(G33,G35) -> 0.26705747 | H34: =H33/SUM(H33,H35) -> 0.29794594 | I34: =I33/SUM(I33,I35) -> 0.30783441 | J34: =J33/SUM(J33,J35) -> 0.32879653 | ... P34: =P33/SUM(P33,P35) -> 0.41960285 | Q34: 0.3 | R34: 0.35 | S34: 0.375 | T34: 0.375 | U34: 0.4
B35: IB Deposits | C35: =CW75 -> 7978268 | D35: =CT75 -> 12471879 | E35: =CO75 -> 13752887 | F35: =CL75 -> 13645091 | G35: =CI75 -> 14215715 | H35: =CD72 -> 16105099 | I35: =CA72 -> 17827140 | J35: =BX72 -> 19130891 | K35: =BS72 -> 20186057 | L35: =BP72 -> 22140712 | M35: =BM72 -> 25544452 | N35: =BE78 -> 26939739 | O35: =BB78 -> 30212286 | P35: =AY78 -> 31515321 | Q35: =Q31-Q33 -> 38068345 | R35: =R31-R33 -> 34465448 | S35: =S31-S33 -> 34796846 | T35: =T31-T33 -> 36536689 | U35: =U31-U33 -> 35952102
B36: IB % of Deposits | C36: =1-C34 -> 0.84532216 | D36: =1-D34 -> 0.83756191 | E36: =1-E34 -> 0.81664755 | F36: =1-F34 -> 0.77760329 | G36: =1-G34 -> 0.73294253 | H36: =1-H34 -> 0.70205406 | I36: =1-I34 -> 0.69216559 | J36: =1-J34 -> 0.67120347 | ... U36: =1-U34 -> 0.6 | AY36: Year Ended December 31,
B37: Cost of IB | C37: =CY75 -> 0.01622871 | D37: =CV75 -> 0.009360017 | E37: =CQ75 -> 0.0077881829 | F37: =CN75 -> 0.0055620736 | G37: =CK75 -> 0.0044666061 | H37: =CF72 -> 0.0040661656 | I37: =CC72 -> 0.0041232076 | J37: =BZ72 -> 0.0044025132 | K37: =BU72 -> 0.0057659106 | L37: =BR72 -> 0.01060273 | M37: =BO72 -> 0.014711688 | N37: =BH78 -> 0.0068576017 | O37: =BD78 -> 0.0022891019 | P37: =BA78 -> 0.0079909705 | Q37: ='Misc Data + Calculations'!AY581 -> 0.0309 | R37: ='Misc Data + Calculations'!AZ581 -> 0.0325 | S37: ='Misc Data + Calculations'!BA581 -> 0.028610236 | T37: ='Misc Data + Calculations'!BB581 -> 0.023697249 | U37: ='Misc Data + Calculations'!BC581 -> 0.019059845 | AY37: 2022 | BB37: 2021 | BE37: 2020 | BM37: Year Ended December 31, | BX37: Year Ended December 31,
B38: Delta to FFR | C38: =C37-C$4 -> 0.01462871 | D38: =D37-D$4 -> 0.007560017 | E38: =E37-E$4 -> 0.0067881829 | F38: =F37-F$4 -> 0.0041620736 | G38: =G37-G$4 -> 0.0033666061 | H38: =H37-H$4 -> 0.0031661656 | I38: =I37-I$4 -> 0.0028232076 | J38: =J37-J$4 -> 0.00040251319 | ... U38: =U37-U$4 -> -0.0059401553 | AX38: ($ in thousands) | AY38: Average Balance | AZ38: Interest | BA38: Average Yield/ Rate | BB38: Average Balance | BC38: Interest | BD38: Average Yield/ Rate | BE38: Average Balance | BG38: Interest | BH38: Average Yield/ Rate | BM38: 2019 | BP38: 2018 | BS38: 2017 | BX38: 2016 | CA38: 2015 | CD38: 2014 | CI38: 2013 | CL38: 2012 | CO38: 2011 | CT38: 2010 | CW38: 2009
B39: Blended Cost of Deposits | C39: =(C37*C35)/(SUM(C33,C35)) -> 0.013718488 | D39: =(D37*D35)/(SUM(D33,D35)) -> 0.0078395938 | E39: =(E37*E35)/(SUM(E33,E35)) -> 0.0063602005 | F39: =(F37*F35)/(SUM(F33,F35)) -> 0.0043250867 | G39: =(G37*G35)/(SUM(G33,G35)) -> 0.0032737656 | H39: =(H37*H35)/(SUM(H33,H35)) -> 0.0028546681 | I39: =(I37*I35)/(SUM(I33,I35)) -> 0.0028539424 | J39: =(J37*J35)/(SUM(J33,J35)) -> 0.0029549821 | ... U39: =(U37*U35)/(SUM(U33,U35)) -> 0.011435907 | AX39: ASSETS | BL39: ($ in thousands) | BM39: Average Balance | BN39: Interest | BO39: Average Yield/ Rate | BP39: Average Balance | BQ39: Interest | BR39: Average Yield/ Rate | BS39: Average Balance | BT39: Interest | BU39: Average Yield/ Rate | BW39: ($ in thousands) | BX39: Average Balance | BY39: Interest | BZ39: Average Yield/ Rate | CA39: Average Balance | CB39: Interest | CC39: Average Yield/ Rate | CD39: Average Balance | CE39: Interest | CF39: Average Yield/ Rate | CI39: Average Balance | CJ39: Interest | CK39: Average Yield Rate | CL39: Average Balance | CM39: Interest | CN39: Average Yield Rate | CO39: Average Balance | CP39: Interest | CQ39: Average Yield Rate | CT39: Average Balance | CU39: Interest | CV39: Average Yield Rate | CW39: Average Balance | CX39: Interest | CY39: Average Yield Rate
B40: % of IBL | C40: =C35/SUM(C35,C42,C48) -> 0.75337475 | D40: =D35/SUM(D35,D42,D48) -> 0.82423658 | E40: =E35/SUM(E35,E42,E48) -> 0.87442876 | F40: =F35/SUM(F35,F42,F48) -> 0.89682229 | G40: =G35/SUM(G35,G42,G48) -> 0.90583879 | H40: =H35/SUM(H35,H42,H48) -> 0.91254056 | I40: =I35/SUM(I35,I42,I48) -> 0.94918789 | J40: =J35/SUM(J35,J42,J48) -> 0.95906622 | ... P40: =P35/SUM(P35,P42,P48) -> 0.97501997 | Q40: 0.89 | R40: =AVERAGE(S40,Q40) -> 0.92 | S40: 0.95 | T40: 0.975 | U40: 0.975 | AX40: Interest-earning assets: | BL40: ASSETS | BW40: ASSETS | CI40: (Dollars in thousands)
B41: Deposit Interest Expense (-) | C41: =C39*C31 -> 129477 | D41: =D39*D31 -> 116737 | E41: =E39*E31 -> 107110 | F41: =F39*F31 -> 75895 | G41: =G39*G31 -> 63496 | H41: =H39*H31 -> 65486 | I41: =I39*I31 -> 73505 | J41: =J39*J31 -> 84224 | ... U41: =U39*U31 -> 685241.47 | AX41: Interest-bearing cash and deposits with banks | AY41: 3127234 | AZ41: 41113 | BA41: 0.0131 | BB41: 6071896 | BC41: 15531 | BD41: 0.0026 | BE41: 4236430 | BG41: 25175 | BH41: 0.0059 | BL41: Interest-earning assets: | BW41: Interest-earning assets: | CH41: ASSETS | CS41: ASSETS
B42: LT Borrowing | C42: =CW91 -> 235570 | D42: =CT91 -> 235570 | E42: =CO91 -> 226808 | F42: =CL91 -> 183285 | G42: =CI91 -> 166690 | H42: =CD86 -> 237738 | I42: =CA86 -> 218353 | J42: =BX86 -> 198589 | K42: =BS89 -> 178882 | L42: =BP89 -> 159185 | M42: =BM89 -> 152445 | N42: =BE93 -> 734921 | O42: =BB93 -> 151955 | P42: =AY93 -> 152325 | Q42: =Q$35*Q46/Q$40 -> 213867.11 | R42: =R$35*R46/R$40 -> 187312.22 | S42: =S$35*S46/S$40 -> 183141.3 | T42: =T$35*T46/T$40 -> 187367.63 | U42: =U$35*U46/U$40 -> 184369.75
B43: Growth | D43: =D42/C42-1 -> 0 | E43: =E42/D42-1 -> -0.037194889 | F43: =F42/E42-1 -> -0.19189358 | G43: =G42/F42-1 -> -0.090542052 | H43: =H42/G42-1 -> 0.42622833 | I43: =I42/H42-1 -> -0.081539342 | J43: =J42/I42-1 -> -0.090513984 | K43: =K42/J42-1 -> -0.099235104 | ... U43: =U42/T42-1 -> -0.016 | AX43: % of IEA | AY43: =AY41/$AY$55 -> 0.05272776 | BB43: =BB41/$BB$55 -> 0.10793256 | BE43: =BE41/$BE$55 -> 0.091618872 | BL43: Interest-bearing cash and deposits with banks | BM43: 3050954 | BN43: 66760 | BO43: 0.0219 | BP43: 2609463 | BQ43: 54804 | BR43: 0.021 | BS43: 2242256 | BT43: 33390 | BU43: 0.0149 | BW43: Interest-bearing cash and deposits with banks | BX43: 1893064 | BY43: 14731 | BZ43: 0.0078 | CA43: 1851604 | CB43: 17939 | CC43: 0.0097 | CD43: 1469200 | CE43: 23214 | CF43: 0.0158 | CH43: Interest-earning assets: | CS43: Interest-earning assets:
B44: Cost | C44: =CY91 -> 0.0327 | D44: =CV91 -> 0.0269 | E44: =CQ91 -> 0.0257 | F44: =CN91 -> 0.021 | G44: =CK91 -> 0.0206 | H44: =CF86 -> 0.0203 | I44: =CC86 -> 0.0212 | J44: =BZ86 -> 0.0253 | K44: =BU89 -> 0.0303 | L44: =BR89 -> 0.0408 | M44: =BO89 -> 0.0436 | N44: =BH93 -> 0.0082 | O44: =BD93 -> 0.0203 | P44: =BA93 -> 0.0367 | Q44: ='Misc Data + Calculations'!AY585 -> 0.0701 | R44: ='Misc Data + Calculations'!AZ585 -> 0.07 | S44: ='Misc Data + Calculations'!BA585 -> 0.0588 | T44: ='Misc Data + Calculations'!BB585 -> 0.0518 | U44: ='Misc Data + Calculations'!BC585 -> 0.0438 | AX44: Resale agreements (1) | AY44: 1398080 | AZ44: 29767 | BA44: 0.0213 | BB44: 2107157 | BC44: 32239 | BD44: 0.0153 | BE44: 1101434 | BG44: 21389 | BH44: 0.0194 | BL44: % of IEA | BM44: =BM43/$BM$55 -> 0.075666993 | BP44: =BP43/$BP$55 -> 0.0710887 | BS44: =BS43/$BS$55 -> 0.065882697 | BW44: % of IEA | BX44: =BX43/$BX$55 -> 0.06048751 | CA44: =CA43/$CA$55 -> 0.065218952 | CD44: =CD43/$CD$55 -> 0.056948875 | CH44: Due from banks and short-term investments | CI44: 1184709 | CJ44: 17340 | CK44: 0.0146 | CL44: 1457153 | CM44: 22316 | CN44: 0.0153 | CO44: 1018490 | CP44: 22575 | CQ44: 0.0222 | CS44: Due from banks and short-term investments | CT44: 828039 | CU44: 9634 | CV44: 0.0116 | CW44: 881282 | CX44: 9047 | CY44: 0.0103
B45: Delta to FFR | C45: =C44-C$4 -> 0.0311 | D45: =D44-D$4 -> 0.0251 | E45: =E44-E$4 -> 0.0247 | F45: =F44-F$4 -> 0.0196 | G45: =G44-G$4 -> 0.0195 | H45: =H44-H$4 -> 0.0194 | I45: =I44-I$4 -> 0.0199 | J45: =J44-J$4 -> 0.0213 | ... U45: =U44-U$4 -> 0.0188 | AX45: % of IEA | AY45: =AY44/$AY$55 -> 0.023572789 | BB45: =BB44/$BB$55 -> 0.037456315 | BE45: =BE44/$BE$55 -> 0.023820089 | BL45: Resale agreements (1) | BM45: 969384 | BN45: 27819 | BO45: 0.0287 | BP45: 1020822 | BQ45: 29328 | BR45: 0.0287 | BS45: 1438767 | BT45: 32095 | BU45: 0.0223 | BW45: Resale agreements (1) | BX45: 1708470 | BY45: 30547 | BZ45: 0.0179 | CA45: 1337274 | CB45: 19799 | CC45: 0.0148 | CD45: 1340411 | CE45: 20323 | CF45: 0.0152 | CH45: % of IEA | CI45: =CI44/CI58 -> 0.054275592 | CL45: =CL44/CL58 -> 0.073440844 | CO45: =CO44/CO58 -> 0.05251734 | CS45: % of IEA | CT45: =CT44/CT58 -> 0.046714527 | CW45: =CW44/CW58 -> 0.068259223
B46: % of IBL | C46: =C42/SUM(C$48,C$42,C$35) -> 0.022244488 | D46: =D42/SUM(D$48,D$42,D$35) -> 0.015568257 | E46: =E42/SUM(E$48,E$42,E$35) -> 0.014420786 | F46: =F42/SUM(F$48,F$42,F$35) -> 0.012046389 | G46: =G42/SUM(G$48,G$42,G$35) -> 0.010621644 | H46: =H42/SUM(H$48,H$42,H$35) -> 0.013470614 | I46: =I42/SUM(I$48,I$42,I$35) -> 0.011625983 | J46: =J42/SUM(J$48,J$42,J$35) -> 0.0099556263 | ... P46: =P42/SUM(P$48,P$42,P$35) -> 0.0047126259 | Q46: 0.005 | R46: 0.005 | S46: 0.005 | T46: 0.005 | U46: 0.005 | AX46: Available-for-sale ("AFS") debt securities (2)(3) | AY46: 6629945 | AZ46: 152514 | BA46: 0.023 | BB46: 8281234 | BC46: 143983 | BD46: 0.0174 | BL46: % of IEA | BM46: =BM45/$BM$55 -> 0.024041783 | BP46: =BP45/$BP$55 -> 0.027809901 | BS46: =BS45/$BS$55 -> 0.042274321 | BW46: % of IEA | BX46: =BX45/$BX$55 -> 0.054589331 | CA46: =CA45/$CA$55 -> 0.047102733 | CD46: =CD45/$CD$55 -> 0.051956778 | CH46: Securities purchased under resale agreements | CI46: 1503014 | CJ46: 21236 | CK46: 0.0141 | CL46: 1267284 | CM46: 20392 | CN46: 0.0161 | CO46: 1023043 | CP46: 19216 | CQ46: 0.0188 | CS46: Securities purchased under resale agreements | CT46: 529817 | CU46: 14208 | CV46: 0.0264 | CW46: 89883 | CX46: 7985 | CY46: 0.0876
B47: LT Borrowing Interest Expense (-) | C47: =C42*C44 -> 7703.139 | D47: =D42*D44 -> 6336.833 | E47: =E42*E44 -> 5828.9656 | F47: =F42*F44 -> 3848.985 | G47: =G42*G44 -> 3433.814 | H47: =H42*H44 -> 4826.0814 | I47: =I42*I44 -> 4629.0836 | J47: =J42*J44 -> 5024.3017 | ... U47: =U42*U44 -> 8075.3951 | AX47: Held-to-maturity ("HTM") debt securities (2)(4) | AY47: 2756382 | AZ47: 46392 | BA47: 0.0168 | BB47: 0 | BC47: 0 | BD47: 0 | BE47: 0 | BG47: 0 | BH47: 0 | BL47: Investment securities (2)(3) | BM47: 2850476 | BN47: 67838 | BO47: 0.0238 | BP47: 2773152 | BQ47: 60911 | BR47: 0.022 | BS47: 3026693 | BT47: 58670 | BU47: 0.0194 | BW47: Investment securities (2)(3) | BX47: 3355086 | BY47: 53399 | BZ47: 0.0159 | CA47: 2847655 | CB47: 41375 | CC47: 0.0145 | CD47: 2540228 | CE47: 44684 | CF47: 0.0176 | CH47: % of IEA | CI47: =CI46/CI58 -> 0.068858238 | CL47: =CL46/CL58 -> 0.063871403 | CO47: =CO46/CO58 -> 0.052752111 | CS47: % of IEA | CT47: =CT46/CT58 -> 0.029890078 | CW47: =CW46/CW58 -> 0.0069618394
B48: ST Borrowing | C48: =CW89 -> 2376201 | D48: =CT89 -> 2423982 | E48: =CO89 -> 1748158 | F48: =CL89 -> 1386557 | G48: =CI89 -> 1311022 | H48: =CD84 -> 1305802 | I48: =CA84 -> 735973 | J48: =BX84 -> 617934 | K48: =BS85 -> 566026 | L48: =BP85 -> 409657 | M48: =BM85 -> 712064 | N48: =BE91 -> 1123617 | O48: =BB91 -> 713218 | P48: =AY91 -> 655098 | Q48: =Q$35*Q52/Q$40 -> 4491209.2 | R48: =R$35*R52/R$40 -> 2809683.2 | S48: =S$35*S52/S$40 -> 1648271.7 | T48: =T$35*T52/T$40 -> 749470.54 | U48: =U$35*U52/U$40 -> 737479.01
B49: Growth | D49: =D48/C48-1 -> 0.020108147 | E49: =E48/D48-1 -> -0.27880735 | F49: =F48/E48-1 -> -0.20684686 | G49: =G48/F48-1 -> -0.054476664 | H49: =H48/G48-1 -> -0.0039816265 | I49: =I48/H48-1 -> -0.43638239 | J49: =J48/I48-1 -> -0.16038496 | K49: =K48/J48-1 -> -0.084002499 | ... U49: =U48/T48-1 -> -0.016 | AX49: Restricted equity securities | AY49: 77963 | AZ49: 3144 | BA49: 0.0403 | BB49: 79404 | BC49: 2081 | BD49: 0.0262 | BI49: 79160 | BL49: Restricted equity securities | BM49: 76854 | BN49: 2468 | BO49: 0.0321 | BP49: 73691 | BQ49: 3146 | BR49: 0.0427 | BS49: 73593 | BT49: 2524 | BU49: 0.0343 | BW49: Investments in FHLB and Federal Reserve Bank stock | BX49: 75260 | BY49: 3427 | BZ49: 0.0455 | CA49: 77460 | CB49: 6077 | CC49: 0.0785 | CD49: 96921 | CE49: 6272 | CF49: 0.0647 | CH49: Investment securities (1)(2) | CI49: 2729019 | CJ49: 43846 | CK49: 0.0161 | CL49: 2475489 | CM49: 58184 | CN49: 0.0235 | CO49: 3116671 | CP49: 89469 | CQ49: 0.0287 | CS49: Investment securities(1)(2)(3) | CT49: 2439034 | CU49: 70052 | CV49: 0.0287 | CW49: 2569792 | CX49: 116688 | CY49: 0.0454
B50: Cost | C50: =CY89 -> 0.042014964 | D50: =CV89 -> 0.032161955 | E50: =CQ89 -> 0.036884538 | F50: =CN89 -> 0.037804432 | G50: =CK89 -> 0.034746938 | H50: =CF84 -> 0.032555472 | I50: =CC84 -> 0.034287943 | J50: =BZ84 -> 0.025248651 | K50: =BU85 -> 0.032207001 | L50: =BR85 -> 0.058475749 | M50: =BO85 -> 0.044998764 | N50: =BH91 -> 0.024084719 | O50: =BD91 -> 0.020922074 | P50: =BA91 -> 0.027350106 | Q50: ='Misc Data + Calculations'!AY583 -> 0.0437 | R50: ='Misc Data + Calculations'!AZ583 -> 0.045 | S50: ='Misc Data + Calculations'!BA583 -> 0.044409449 | T50: ='Misc Data + Calculations'!BB583 -> 0.042286046 | U50: ='Misc Data + Calculations'!BC583 -> 0.039588372 | AX50: Securities | AY50: =SUM(AY46:AY49) -> 9464290 | AZ50: =SUM(AZ46:AZ49) -> 202050 | BA50: =AZ50/AY50 -> 0.02134867 | BB50: =SUM(BB46:BB49) -> 8360638 | BC50: =SUM(BC46:BC49) -> 146064 | BD50: =BC50/BB50 -> 0.017470437 | BE50: =SUM(BI49:BI50) -> 4102828 | BG50: =SUM(BK49:BK50) -> 0 | BH50: =BG50/BE50 -> 0 | BI50: 4023668 | BL50: Securities | BM50: =SUM(BM47:BM49) -> 2927330 | BO50: =SUM(BN47:BN49)/BM50 -> 0.024017108 | BP50: =SUM(BP47:BP49) -> 2846843 | BR50: =SUM(BQ47:BQ49)/BP50 -> 0.022501065 | BS50: =SUM(BS47:BS49) -> 3100286 | BU50: =SUM(BT47:BT49)/BS50 -> 0.019738179 | BW50: Securities | BX50: =SUM(BX47:BX49) -> 3430346 | BZ50: =SUM(BY47:BY49)/BX50 -> 0.016565676 | CA50: =SUM(CA47:CA49) -> 2925115 | CC50: =SUM(CB47:CB49)/CA50 -> 0.016222268 | CD50: =SUM(CD47:CD49) -> 2637149 | CF50: =SUM(CE47:CE49)/CD50 -> 0.019322382 | CH50: FHLB and FRB stock | CI50: 134918 | CJ50: 6869 | CK50: 0.0509 | CL50: 171816 | CM50: 4673 | CN50: 0.0272 | CO50: 197774 | CP50: 3390 | CQ50: 0.0171 | CS50: FHLB and FRB stock | CT50: 219710 | CU50: 3348 | CV50: 0.0152 | CW50: 137001 | CX50: 2337 | CY50: 0.0171
B51: Delta to FFR | C51: =C50-C$4 -> 0.040414964 | D51: =D50-D$4 -> 0.030361955 | E51: =E50-E$4 -> 0.035884538 | F51: =F50-F$4 -> 0.036404432 | G51: =G50-G$4 -> 0.033646938 | H51: =H50-H$4 -> 0.031655472 | I51: =I50-I$4 -> 0.032987943 | J51: =J50-J$4 -> 0.021248651 | ... U51: =U50-U$4 -> 0.014588372 | AX51: % of IEA | AY51: =AY50/$AY$55 -> 0.15957578 | BB51: =BB50/$BB$55 -> 0.14861669 | BE51: =BE50/$BE$55 -> 0.088729538 | BL51: % of IEA | BM51: =BM50/$BM$55 -> 0.072600983 | BP51: =BP50/$BP$55 -> 0.077555561 | BS51: =BS50/$BS$55 -> 0.091093615 | BW51: % of IEA | BX51: =BX50/BX55 -> 0.10960701 | CA51: =CA50/$CA$55 -> 0.10303117 | CD51: =CD50/$CD$55 -> 0.10222071 | CH51: Securities | CI51: =SUM(CI49:CI50) -> 2863937 | CK51: =SUM(CJ49:CJ50)/CI51 -> 0.017708141 | CL51: =SUM(CL49:CL50) -> 2647305 | CN51: =SUM(CM49:CM50)/CL51 -> 0.02374377 | CO51: =SUM(CO49:CO50) -> 3314445 | CQ51: =SUM(CP49:CP50)/CO51 -> 0.028016455 | CS51: Securities | CT51: =SUM(CT49:CT50) -> 2658744 | CV51: =SUM(CU49:CU50)/CT51 -> 0.02760702 | CW51: =SUM(CW49:CW50) -> 2706793 | CY51: =SUM(CX49:CX50)/CW51 -> 0.043972701
B52: % of IBL | C52: =C48/SUM(C$48,C$42,C$35) -> 0.22438076 | D52: =D48/SUM(D$48,D$42,D$35) -> 0.16019516 | E52: =E48/SUM(E$48,E$42,E$35) -> 0.11115045 | F52: =F48/SUM(F$48,F$42,F$35) -> 0.091131325 | G52: =G48/SUM(G$48,G$42,G$35) -> 0.083539561 | H52: =H48/SUM(H$48,H$42,H$35) -> 0.073988821 | I52: =I48/SUM(I$48,I$42,I$35) -> 0.039186132 | J52: =J48/SUM(J$48,J$42,J$35) -> 0.030978151 | ... P52: =P48/SUM(P$48,P$42,P$35) -> 0.020267401 | Q52: 0.105 | R52: 0.075 | S52: 0.045 | T52: 0.02 | U52: 0.02 | AX52: Loans (5)(6) | AY52: 45319458 | AZ52: 2048301 | BA52: 0.0452 | BB52: 39716697 | BC52: 1424900 | BD52: 0.0359 | BE52: 36799017 | BG52: 1464382 | BH52: 0.0398 | BL52: Loans (4)(5) | BM52: 33373136 | BN52: 1717415 | BO52: 0.0515 | BP52: 30230014 | BQ52: 1503514 | BR52: 0.0497 | BS52: 27252756 | BT52: 1198440 | BU52: 0.044 | BW52: Loans (4)(5) | BX52: 24264895 | BY52: 1035377 | BZ52: 0.0427 | CA52: 22276589 | CB52: 968625 | CC52: 0.0435 | CD52: 20351818 | CE52: 1059205 | CF52: 0.052 | CH52: % of IEA | CI52: =CI51/CI58 -> 0.1312068 | CL52: =CL51/CL58 -> 0.13342478 | CO52: =CO51/CO58 -> 0.17090579 | CS52: % of IEA | CT52: =CT51/CT58 -> 0.14999531 | CW52: =CW51/CW58 -> 0.2096532
B53: ST Borrowing Interest Expense (-) | C53: =C48*C50 -> 99836 | D53: =D48*D50 -> 77960 | E53: =E48*E50 -> 64480 | F53: =F48*F50 -> 52418 | G53: =G48*G50 -> 45554 | H53: =H48*H50 -> 42511 | I53: =I48*I50 -> 25235 | J53: =J48*J50 -> 15602 | ... U53: =U48*U50 -> 29195.593 | AX53: % of IEA | AY53: =AY52/$AY$55 -> 0.76412367 | BB53: =BB52/$BB$55 -> 0.70599444 | BE53: =BE52/$BE$55 -> 0.7958315 | BL53: % of IEA | BM53: =BM52/$BM$55 -> 0.82769024 | BP53: =BP52/$BP$55 -> 0.82354584 | BS53: =BS52/$BS$55 -> 0.80074937 | BW53: % of IEA | BX53: =BX52/$BX$55 -> 0.77531615 | CA53: =CA52/$CA$55 -> 0.78464714 | CD53: =CD52/$CD$55 -> 0.78887363 | CH53: Loans receivable (1)(3) | CI53: 13734759 | CJ53: 584164 | CK53: 0.0425 | CL53: 11023745 | CM53: 515378 | CN53: 0.0468 | CO53: 9668106 | CP53: 478724 | CQ53: 0.0495 | CS53: Loans receivable(2)(4) | CT53: 8634283 | CU53: 479451 | CV53: 0.0555 | CW53: 8355825 | CX53: 452019 | CY53: 0.0541
B54: Provision for Credit Losses (-) | C54: =AY124 -> 528666 | D54: =AZ124 -> 200159 | E54: =BA124 -> 95006 | F54: =BB124 -> 65184 | G54: =BC124 -> 22364 | H54: =BD124 -> 49158 | I54: =BE124 -> 14217 | J54: =BF124 -> 27479 | ... P54: =BL124 -> 73500 | Q54: =Q55*SUM(Q5,Q11,Q17,Q23) -> 127129.91 | R54: =R55*SUM(R5,R11,R17,R23) -> 119303.47 | S54: =S55*SUM(S5,S11,S17,S23) -> 93951.485 | T54: =T55*SUM(T5,T11,T17,T23) -> 98649.059 | U54: =U55*SUM(U5,U11,U17,U23) -> 101115.29
B55: % of IEAs | C55: =C54/SUM(C5,C11,C17,C23) -> 0.040947541 | D55: =D54/SUM(D5,D11,D17,D23) -> 0.011292141 | E55: =E54/SUM(E5,E11,E17,E23) -> 0.0048988821 | F55: =F54/SUM(F5,F11,F17,F23) -> 0.0032852885 | G55: =G54/SUM(G5,G11,G17,G23) -> 0.0010245717 | H55: =H54/SUM(H5,H11,H17,H23) -> 0.0019054539 | I55: =I54/SUM(I5,I11,I17,I23) -> 0.00050076465 | J55: =J54/SUM(J5,J11,J17,J23) -> 0.00087801379 | ... P55: =P54/SUM(P5,P11,P17,P23) -> 0.001239271 | Q55: 0.002 | R55: 0.002 | S55: 0.0015 | T55: 0.0015 | U55: 0.0015 | AX55: Total interest-earning assets | AY55: 59309062 | AZ55: 2321231 | BA55: 0.0391 | BB55: 56256388 | BC55: 1618734 | BD55: 0.0288 | BE55: 46239709 | BG55: 1595042 | BH55: 0.0345 | BL55: Total interest-earning assets | BM55: 40320804 | BN55: 1882300 | BO55: 0.0467 | BP55: 36707142 | BQ55: 1651703 | BR55: 0.045 | BS55: 34034065 | BT55: 1325119 | BU55: 0.0389 | BW55: Total interest-earning assets | BX55: 31296775 | BY55: 1137481 | BZ55: 0.0363 | CA55: 28390582 | CB55: 1053815 | CC55: 0.0371 | CD55: 25798578 | CE55: 1153698 | CF55: 0.0447 | CH55: Loans receivable - covered (3) | CI55: 2541238 | CJ55: 395230 | CK55: 0.1555 | CL55: 3445693 | CM55: 430152 | CN55: 0.1248 | CO55: 4369320 | CP55: 467074 | CQ55: 0.1069 | CS55: Loans receivable - covered(2) | CT55: 5074631 | CU55: 519138 | CV55: 0.1023 | CW55: 877029 | CX55: 135144 | CY55: 0.1541
B56: Implied NIM | C56: =(SUM(C10,C16,C22,C28)-SUM(C41,C47,C53))/SUM(C5,C11,C17,C23) -> 0.037652381 | D56: =(SUM(D10,D16,D22,D28)-SUM(D41,D47,D53))/SUM(D5,D11,D17,D23) -> 0.050466666 | E56: =(SUM(E10,E16,E22,E28)-SUM(E41,E47,E53))/SUM(E5,E11,E17,E23) -> 0.046566437 | F56: =(SUM(F10,F16,F22,F28)-SUM(F41,F47,F53))/SUM(F5,F11,F17,F23) -> 0.046313915 | G56: =(SUM(G10,G16,G22,G28)-SUM(G41,G47,G53))/SUM(G5,G11,G17,G23) -> 0.043802889 | H56: =(SUM(H10,H16,H22,H28)-SUM(H41,H47,H53))/SUM(H5,H11,H17,H23) -> 0.040312883 | I56: =(SUM(I10,I16,I22,I28)-SUM(I41,I47,I53))/SUM(I5,I11,I17,I23) -> 0.03349233 | J56: =(SUM(J10,J16,J22,J28)-SUM(J41,J47,J53))/SUM(J5,J11,J17,J23) -> 0.03302047 | ... U56: =(SUM(U10,U16,U22,U28)-SUM(U41,U47,U53))/SUM(U5,U11,U17,U23) -> 0.037823592 | AB56: =AVERAGE(C56:P56) -> 0.038012372 | AC56: =AVERAGE(Q56:U56) -> 0.037976768 | AX56: Noninterest-earning assets: | AY56: =SUM(AY53,AY51,AY45,AY43) -> 1 | BB56: =SUM(BB53,BB51,BB45,BB43) -> 1 | BE56: =SUM(BE53,BE51,BE45,BE43) -> 1 | BL56: Noninterest-earning assets: | BW56: Noninterest-earning assets: | CH56: Loans (4)(5) | CI56: =SUM(CI53:CI55) -> 16275997 | CK56: =SUM(CJ53:CJ55)/CI56 -> 0.060174132 | CL56: =SUM(CL53:CL55) -> 14469438 | CN56: =SUM(CM53:CM55)/CL56 -> 0.065346698 | CO56: =SUM(CO53:CO55) -> 14037426 | CQ56: =SUM(CP53:CP55)/CO56 -> 0.067376882 | CS56: Loans (4)(5) | CT56: =SUM(CT53:CT55) -> 13708914 | CV56: =SUM(CU53:CU55)/CT56 -> 0.072842313 | CW56: =SUM(CW53:CW55) -> 9232854 | CY56: =SUM(CX53:CX55)/CW56 -> 0.063594962
A57: x | B57: Net Interest Income | C57: =SUM(C10,C16,C22,C28)-SUM(C41,C47,C53)-C54 -> -42543.184 | D57: =SUM(D10,D16,D22,D28)-SUM(D41,D47,D53)-D54 -> 694388.59 | E57: =SUM(E10,E16,E22,E28)-SUM(E41,E47,E53)-E54 -> 808075.72 | F57: =SUM(F10,F16,F22,F28)-SUM(F41,F47,F53)-F54 -> 853738.73 | G57: =SUM(G10,G16,G22,G28)-SUM(G41,G47,G53)-G54 -> 933750.43 | H57: =SUM(H10,H16,H22,H28)-SUM(H41,H47,H53)-H54 -> 990857.06 | I57: =SUM(I10,I16,I22,I28)-SUM(I41,I47,I53)-I54 -> 936649.75 | J57: =SUM(J10,J16,J22,J28)-SUM(J41,J47,J53)-J54 -> 1005955.2 | ... U57: =SUM(U10,U16,U22,U28)-SUM(U41,U47,U53)-U54 -> 2448580.3 | AX57: Cash and due from banks | AY57: 652673 | BB57: 615255 | BE57: 528406 | BL57: Cash and due from banks | BM57: 471060 | BP57: 445768 | BS57: 395092 | BW57: Cash and due from banks | BX57: 365104 | CA57: 342606 | CD57: 322581 | CH57: % of IEA | CI57: =CI56/CI58 -> 0.74565937 | CL57: =CL56/CL58 -> 0.72926298 | CO57: =CO56/CO58 -> 0.72382476 | CS57: % of IEA | CT57: =CT56/CT58 -> 0.77340008 | CW57: =CW56/CW58 -> 0.71512574
B58: Deposit Account Fees (+) | C58: =AY119 -> 22326 | D58: =AZ119 -> 32634 | E58: =BA119 -> 31510 | F58: =BB119 -> 30906 | G58: =BC119 -> 32036 | H58: =BD119 -> 37866 | I58: =BE119 -> 39495 | J58: =BF119 -> 41178 | ... P58: =BL119 -> 88435 | Q58: =Q59*Q31 -> 81575.024 | R58: =R59*R31 -> 79535.649 | S58: =S59*S31 -> 83512.431 | T58: =T59*T31 -> 87688.053 | U58: =U59*U31 -> 89880.254 | AX58: Allowance for loan losses | AY58: -559746 | BB58: -592211 | BE58: -577560 | BL58: Allowance for loan losses | BM58: -330125 | BP58: -298600 | BS58: -272765 | BW58: Allowance for loan losses | BX58: -262804 | CA58: -263143 | CD58: -254616 | CH58: Total interest-earning assets | CI58: 21827657 | CJ58: 1068685 | CK58: 0.049 | CL58: 19841180 | CM58: 1051095 | CN58: 0.053 | CO58: 19393404 | CP58: 1080448 | CQ58: 0.0557 | CS58: Total interest-earning assets | CT58: 17725514 | CU58: 1095831 | CV58: 0.0618 | CW58: 12910812 | CX58: 723220 | CY58: 0.056
B59: % of Deposits | C59: =C58/C31 -> 0.0023655087 | D59: =D58/D31 -> 0.00219157 | E59: =E58/E31 -> 0.0018710664 | F59: =F58/F31 -> 0.001761264 | G59: =G58/G31 -> 0.0016517317 | H59: =H58/H31 -> 0.001650656 | I59: =I58/I31 -> 0.0015334529 | J59: =J58/J31 -> 0.0014447219 | ... P59: =P58/P31 -> 0.0016286498 | Q59: 0.0015 | R59: 0.0015 | S59: 0.0015 | T59: 0.0015 | U59: 0.0015 | AX59: Other assets | AY59: 3436293 | BB59: 2971659 | BE59: 2747238 | BL59: Other assets | BM59: 2023146 | BP59: 1688259 | BS59: 1631221 | BW59: Other assets | BX59: 1770298 | CA59: 1858412 | CD59: 1786427 | CH59: Noninterest-earning assets: | CS59: Noninterest-earning assets:
B60: Wealth Management Fees (+) | C60: =AY121 -> 0 | D60: =AZ121 -> 0 | E60: =BA121 -> 0 | F60: =BB121 -> 0 | G60: =BC121 -> 0 | H60: =BD121 -> 16162 | I60: =BE121 -> 18268 | J60: =BF121 -> 13240 | ... P60: =BL121 -> 27565 | Q60: =Q61*Q31 -> 27191.675 | R60: =R61*R31 -> 26511.883 | S60: =S61*S31 -> 27837.477 | T60: =T61*T31 -> 29229.351 | U60: =U61*U31 -> 29960.085
B61: % of Deposits | C61: =C60/C31 -> 0 | D61: =D60/D31 -> 0 | E61: =E60/E31 -> 0 | F61: =F60/F31 -> 0 | G61: =G60/G31 -> 0 | H61: =H60/H31 -> 0.00070453449 | I61: =I60/I31 -> 0.00070928264 | J61: =J60/J31 -> 0.00046452274 | ... P61: =P60/P31 -> 0.00050764666 | Q61: 0.0005 | R61: 0.0005 | S61: 0.0005 | T61: 0.0005 | U61: 0.0005 | BL61: Total assets | BM61: 42484885 | BP61: 38542569 | BS61: 35787613 | BW61: Total assets | BX61: 33169373 | CA61: 30328457 | CD61: 27652970 | CH61: Cash and cash equivalents | CI61: 306551 | CL61: 255975 | CO61: 271393 | CS61: Cash and cash equivalents | CT61: 365041 | CW61: 147694
B62: Lending Fees (+) | C62: =AY118 -> 14624 | D62: =AZ118 -> 20342 | E62: =BA118 -> 22347 | F62: =BB118 -> 27935 | G62: =BC118 -> 31484 | H62: =BD118 -> 47939 | I62: =BE118 -> 54014 | J62: =BF118 -> 65112 | ... P62: =BL118 -> 79208 | Q62: =Q63*Q17 -> 97890.029 | R62: =R63*R17 -> 95442.779 | S62: =S63*S17 -> 100214.92 | T62: =T63*T17 -> 105225.66 | U62: =U63*U17 -> 107856.3 | BL62: LIABILITIES AND STOCKHOLDERS' EQUITY | BW62: LIABILITIES AND STOCKHOLDERS' EQUITY | CH62: Allowance for loan losses | CI62: -241049 | CL62: -228355 | CO62: -228160 | CS62: Allowance for loan losses | CT62: -252318 | CW62: -216775
B63: % of Loans | C63: =C62/C17 -> 0.0015839089 | D63: =D62/D17 -> 0.001483852 | E63: =E62/E17 -> 0.0015919585 | F63: =F62/F17 -> 0.0019306209 | G63: =G62/G17 -> 0.0019343823 | H63: =H62/H17 -> 0.0023555144 | I63: =I62/I17 -> 0.002424698 | J63: =J62/J17 -> 0.0026833827 | ... P63: =P62/P17 -> 0.0017477702 | Q63: 0.002 | R63: 0.002 | S63: 0.002 | T63: 0.002 | U63: 0.002 | AX63: Total assets | AY63: 62838282 | BB63: 59251091 | BE63: 48937793 | BL63: Interest-bearing liabilities: | BW63: Interest-bearing liabilities: | CH63: Other assets | CI63: 1667533 | CL63: 1961743 | CO63: 2136484 | CS63: Other assets | CT63: 2339872 | CW63: 997214
B64: Forex Income (+) | C64: =AY120 -> 1201 | D64: =AZ120 -> 3171 | E64: =BA120 -> 9143 | F64: =BB120 -> 7166 | G64: =BC120 -> 12658 | H64: =BD120 -> 10991 | I64: =BE120 -> 16493 | J64: =BF120 -> 16781 | ... P64: =BL120 -> 48158 | Q64: =Q65*Q17 -> 48945.015 | R64: =R65*R17 -> 47721.389 | S64: =S65*S17 -> 50107.459 | T64: =T65*T17 -> 52612.832 | U64: =U65*U17 -> 53928.152 | AX64: IEAs as a % of Total Assets | AY64: =AY55/AY63 -> 0.94383647 | BB64: =BB55/BB63 -> 0.94945742 | BE64: =BE55/BE63 -> 0.94486707 | BL64: Checking deposits (6) | BM64: 5244867 | BN64: 58168 | BO64: 0.0111 | BP64: 4477793 | BQ64: 34657 | BR64: 0.0077 | BS64: 3951930 | BT64: 18305 | BU64: 0.0046 | BW64: Checking deposits | BX64: 3495094 | BY64: 12640 | BZ64: 0.0036 | CA64: 2795379 | CB64: 8453 | CC64: 0.003 | CD64: 2179428 | CE64: 5431 | CF64: 0.0025 | CH64: Total assets | CI64: 23560692 | CL64: 21830543 | CO64: 21573121 | CS64: Total assets | CT64: 20178109 | CW64: 13838945
B65: % of Loans | C65: =C64/C17 -> 0.00013007896 | D65: =D64/D17 -> 0.00023130935 | E65: =E64/E17 -> 0.00065133024 | F65: =F64/F17 -> 0.00049525075 | G65: =G64/G17 -> 0.00077770965 | H65: =H64/H17 -> 0.00054005003 | I65: =I64/I17 -> 0.00074037367 | J65: =J64/J17 -> 0.00069157522 | ... P65: =P64/P17 -> 0.0010626341 | Q65: 0.001 | R65: 0.001 | S65: 0.001 | T65: 0.001 | U65: 0.001
B66: Other (+) | C66: =AY122 -> 352802 | D66: =AZ122 -> -16877 | E66: =BA122 -> -52076 | F66: =BB122 -> -71625 | G66: =BC122 -> -168646 | H66: -124672 | I66: 55113 | J66: 46607 | K66: =BG122 -> 135172 | L66: =BH122 -> 76931 | M66: =BI122 -> 63993 | N66: =BJ122 -> 72693 | O66: =BK122 -> 62202 | P66: =BL122 -> 55300 | Q66: =Q67*SUM(Q5,Q11,Q17,Q23) -> 95347.431 | R66: =R67*SUM(R5,R11,R17,R23) -> 89477.605 | S66: =S67*SUM(S5,S11,S17,S23) -> 93951.485 | T66: =T67*SUM(T5,T11,T17,T23) -> 98649.059 | U66: =U67*SUM(U5,U11,U17,U23) -> 101115.29 | AX66: LIABILITIES AND STOCKHOLDERS' EQUITY | BL66: Money market deposits (6) | BM66: 8220236 | BN66: 111081 | BO66: 0.0135 | BP66: 7985526 | BQ66: 83696 | BR66: 0.0105 | BS66: 8026347 | BT66: 44181 | BU66: 0.0055 | BW66: Money market deposits | BX66: 7679695 | BY66: 27094 | BZ66: 0.0035 | CA66: 6763979 | CB66: 18988 | CC66: 0.0028 | CD66: 5958461 | CE66: 16001 | CF66: 0.0027 | CH66: LIABILITIES AND STOCKHOLDERS' EQUITY | CS66: LIABILITIES AND STOCKHOLDERS' EQUITY
B67: % of IEAs | C67: =C66/SUM(C5,C11,C17,C23) -> 0.027326089 | D67: =D66/SUM(D5,D11,D17,D23) -> -0.00095213036 | E67: =E66/SUM(E5,E11,E17,E23) -> -0.0026852429 | F67: =F66/SUM(F5,F11,F17,F23) -> -0.0036099163 | G67: =G66/SUM(G5,G11,G17,G23) -> -0.007726253 | H67: =H66/SUM(H5,H11,H17,H23) -> -0.0048325144 | I67: =I66/SUM(I5,I11,I17,I23) -> 0.0019412423 | J67: =J66/SUM(J5,J11,J17,J23) -> 0.001489195 | ... P67: =P66/SUM(P5,P11,P17,P23) -> 0.00093240389 | Q67: 0.0015 | R67: 0.0015 | S67: 0.0015 | T67: 0.0015 | U67: 0.0015
B68: Non-interest expenses (-) | C68: =AY123 -> 243254 | D68: =AZ123 -> 477916 | E68: =BA123 -> 435610 | F68: =BB123 -> 422533 | G68: =BC123 -> 415511 | H68: =BD123 -> 532983 | I68: =BE123 -> 540884 | J68: =BF123 -> 615889 | ... P68: =BL123 -> 859393 | Q68: =(SUM(Q10,Q16,Q22,Q28)+SUM(Q58,Q60,Q62,Q64,Q66)-Q54)*Q69 -> 1053578.3 | R68: =(SUM(R10,R16,R22,R28)+SUM(R58,R60,R62,R64,R66)-R54)*R69 -> 1226512.2 | S68: =(SUM(S10,S16,S22,S28)+SUM(S58,S60,S62,S64,S66)-S54)*S69 -> 1337458.2 | T68: =(SUM(T10,T16,T22,T28)+SUM(T58,T60,T62,T64,T66)-T54)*T69 -> 1313035.5 | U68: =(SUM(U10,U16,U22,U28)+SUM(U58,U60,U62,U64,U66)-U54)*U69 -> 1243841.5
B69: % Efficiency Ratio | C69: =C68/(SUM(C10,C16,C22,C28)+SUM(C58,C60,C62,C64,C66)-C54) -> 0.41551625 | D69: =D68/(SUM(D10,D16,D22,D28)+SUM(D58,D60,D62,D64,D66)-D54) -> 0.51130831 | E69: =E68/(SUM(E10,E16,E22,E28)+SUM(E58,E60,E62,E64,E66)-E54) -> 0.43717566 | F69: =F68/(SUM(F10,F16,F22,F28)+SUM(F58,F60,F62,F64,F66)-F54) -> 0.43103178 | G69: =G68/(SUM(G10,G16,G22,G28)+SUM(G58,G60,G62,G64,G66)-G54) -> 0.43565287 | H69: =H68/(SUM(H10,H16,H22,H28)+SUM(H58,H60,H62,H64,H66)-H54) -> 0.4880948 | I69: =I68/(SUM(I10,I16,I22,I28)+SUM(I58,I60,I62,I64,I66)-I54) -> 0.44211475 | J69: =J68/(SUM(J10,J16,J22,J28)+SUM(J58,J60,J62,J64,J66)-J54) -> 0.47605921 | ... P69: =P68/(SUM(P10,P16,P22,P28)+SUM(P58,P60,P62,P64,P66)-P54) -> 0.33749314 | Q69: 0.275 | R69: 0.325 | S69: 0.35 | T69: 0.35 | U69: 0.35
B70: Tax Expense (-) | C70: =AY125 -> 22714 | D70: =AZ125 -> 91345 | E70: =BA125 -> 138100 | F70: =BB125 -> 143942 | G70: =BC125 -> 130805 | H70: =BD125 -> 101145 | I70: =BE125 -> 194044 | J70: =BF125 -> 140511 | ... P70: =BL125 -> 283571 | Q70: =(SUM(Q57,Q58,Q60,Q62,Q64,Q66)-Q68)*Q71 -> 291909.63 | R70: =(SUM(R57,R58,R60,R62,R64,R66)-R68)*R71 -> 270416.33 | S70: =(SUM(S57,S58,S60,S62,S64,S66)-S68)*S71 -> 294910.85 | T70: =(SUM(T57,T58,T60,T62,T64,T66)-T68)*T71 -> 321568.32 | U70: =(SUM(U57,U58,U60,U62,U64,U66)-U68)*U71 -> 333370.56 | AX70: Interest-bearing liabilities: | BL70: Saving deposits (6) | BM70: 2118060 | BN70: 9626 | BO70: 0.0045 | BP70: 2245644 | BQ70: 8621 | BR70: 0.0038 | BS70: 2369398 | BT70: 6431 | BU70: 0.0027 | BW70: Saving deposits | BX70: 2104060 | BY70: 4719 | BZ70: 0.0022 | CA70: 1785085 | CB70: 3468 | CC70: 0.0019 | CD70: 1748465 | CE70: 2971 | CF70: 0.0017 | CH70: Interest-bearing liabilities: | CS70: Interest-bearing liabilities:
B71: Tax % | C71: =C70/(SUM(C57,C58,C62,C64,C66)-C68) -> 0.21600327 | D71: =D70/(SUM(D57,D58,D62,D64,D66)-D68) -> 0.35717555 | E71: =E70/(SUM(E57,E58,E62,E64,E66)-E68) -> 0.36020788 | F71: =F70/(SUM(F57,F58,F62,F64,F66)-F68) -> 0.33821934 | G71: =G70/(SUM(G57,G58,G62,G64,G66)-G68) -> 0.30721883 | H71: =H70/(SUM(H57,H58,H62,H64,H66)-H68) -> 0.23522199 | I71: =I70/(SUM(I57,I58,I62,I64,I66)-I68) -> 0.34596302 | J71: =J70/(SUM(J57,J58,J62,J64,J66)-J68) -> 0.25102715 | ... P71: =P70/(SUM(P57,P58,P62,P64,P66)-P68) -> 0.20487783 | Q71: 0.21 | R71: 0.21 | S71: 0.21 | T71: 0.21 | U71: 0.21 | AX71: Checking deposits | AY71: 6696200 | AZ71: 29808 | BA71: 0.0045 | BB71: 6543817 | BC71: 13023 | BD71: 0.002 | BE71: 5357934 | BG71: 24213 | BH71: 0.0045 | BL71: Time deposits (6) | BM71: 9961289 | BN71: 196927 | BO71: 0.0198 | BP71: 7431749 | BQ71: 107778 | BR71: 0.0145 | BS71: 5838382 | BT71: 47474 | BU71: 0.0081 | BW71: Time deposits | BX71: 5852042 | BY71: 39771 | BZ71: 0.0068 | CA71: 6482697 | CB71: 42596 | CC71: 0.0066 | CD71: 6218745 | CE71: 41083 | CF71: 0.0066 | CH71: Checking accounts | CI71: 1487844 | CJ71: 3556 | CK71: 0.0024 | CL71: 1059517 | CM71: 3163 | CN71: 0.003 | CO71: 854079 | CP71: 3009 | CQ71: 0.0035 | CS71: Checking accounts | CT71: 677529 | CU71: 2349 | CV71: 0.0035 | CW71: 398619 | CX71: 1507 | CY71: 0.0038
A72: x | B72: Net Income | C72: =SUM(C57,C58,C62,C64,C66,C60)-C68-C70 -> 82441.816 | D72: =SUM(D57,D58,D62,D64,D66,D60)-D68-D70 -> 164397.59 | E72: =SUM(E57,E58,E62,E64,E66,E60)-E68-E70 -> 245289.72 | F72: =SUM(F57,F58,F62,F64,F66,F60)-F68-F70 -> 281645.73 | G72: =SUM(G57,G58,G62,G64,G66,G60)-G68-G70 -> 294966.43 | H72: =SUM(H57,H58,H62,H64,H66,H60)-H68-H70 -> 345015.06 | I72: =SUM(I57,I58,I62,I64,I66,I60)-I68-I70 -> 385104.75 | J72: =SUM(J57,J58,J62,J64,J66,J60)-J68-J70 -> 432473.23 | ... P72: =SUM(P57,P58,P62,P64,P66,P60)-P68-P70 -> 1128092 | Q72: =(SUM(Q57,Q58,Q60,Q62,Q64,Q66)-Q68)-Q70 -> 1098136.2 | R72: =(SUM(R57,R58,R60,R62,R64,R66)-R68)-R70 -> 1017280.5 | S72: =(SUM(S57,S58,S60,S62,S64,S66)-S68)-S70 -> 1109426.5 | T72: =(SUM(T57,T58,T60,T62,T64,T66)-T68)-T70 -> 1209709.4 | U72: =(SUM(U57,U58,U60,U62,U64,U66)-U68)-U70 -> 1254108.3 | BL72: Interest Bearing Deposits | BM72: =SUM(BM64:BM71) -> 25544452 | BO72: =SUM(BN64:BN71)/BM72 -> 0.014711688 | BP72: =SUM(BP64:BP71) -> 22140712 | BR72: =SUM(BQ64:BQ71)/BP72 -> 0.01060273 | BS72: =SUM(BS64:BS71) -> 20186057 | BU72: =SUM(BT64:BT71)/BS72 -> 0.0057659106 | BW72: Interest Bearing Deposits | BX72: =SUM(BX64:BX71) -> 19130891 | BZ72: =SUM(BY64:BY71)/BX72 -> 0.0044025132 | CA72: =SUM(CA64:CA71) -> 17827140 | CC72: =SUM(CB64:CB71)/CA72 -> 0.0041232076 | CD72: =SUM(CD64:CD71) -> 16105099 | CF72: =SUM(CE64:CE71)/CD72 -> 0.0040661656 | CH72: Money market accounts | CI72: 5217666 | CJ72: 15019 | CK72: 0.0029 | CL72: 4883413 | CM72: 16984 | CN72: 0.0035 | CO72: 4429567 | CP72: 20610 | CQ72: 0.0047 | CS72: Money market accounts | CT72: 3974936 | CU72: 29514 | CV72: 0.0074 | CW72: 2035821 | CX72: 25583 | CY72: 0.0126
Q73: =Q72/P72-1 -> -0.026554411 | R73: =R72/Q72-1 -> -0.07362996 | S73: =S72/R72-1 -> 0.090580756 | T73: =T72/S72-1 -> 0.090391629 | U73: =U72/T72-1 -> 0.036702118 | AX73: Money market deposits | AY73: 12443437 | AZ73: 107442 | BA73: 0.0086 | BB73: 12428025 | BC73: 15041 | BD73: 0.0012 | BE73: 9881284 | BG73: 42720 | BH73: 0.0043 | BL73: % of Deposits | BM73: =BM72/SUM(BM72,BM75) -> 0.70864156 | BP73: =BP72/SUM(BP72,BP75) -> 0.66628186 | BS73: =BS72/SUM(BS72,BS75) -> 0.65509847 | BW73: % of Deposits | BX73: =BX72/SUM(BX72,BX75) -> 0.67120347 | CA73: =CA72/SUM(CA72,CA75) -> 0.69216559 | CD73: =CD72/SUM(CD72,CD75) -> 0.70205406 | CH73: Savings deposits | CI73: 1546188 | CJ73: 2961 | CK73: 0.0019 | CL73: 1267059 | CM73: 2795 | CN73: 0.0022 | CO73: 1045546 | CP73: 2988 | CQ73: 0.0029 | CS73: Savings deposits | CT73: 967953 | CU73: 3986 | CV73: 0.0041 | CW73: 506706 | CX73: 3322 | CY73: 0.0066
S74: =(U72/P72)^(1/5) -1 -> 0.021405287 | AX74: Saving deposits | AY74: 2901940 | AZ74: 8550 | BA74: 0.0029 | BB74: 2746933 | BC74: 7496 | BD74: 0.0027 | BE74: 2234913 | BG74: 6398 | BH74: 0.0029 | BL74: % of IBLs | BM74: =BM72/BM91 -> 0.96726456 | BN74: Blended Cost of Deposits | BO74: =SUM(BN64:BN71)/SUM(BM72,BM75) -> 0.010425313 | BP74: =BP72/BP91 -> 0.97495142 | BQ74: Blended Cost of Deposits | BR74: =SUM(BQ64:BQ71)/SUM(BP72,BP75) -> 0.0070644069 | BS74: =BS72/BS91 -> 0.9644112 | BT74: Blended Cost of Deposits | BU74: =SUM(BT64:BT71)/SUM(BS72,BS75) -> 0.0037772392 | BW74: % of IBLs | BX74: =BX72/BX90 -> 0.95906622 | BY74: Blended Cost of Deposits | BZ74: =SUM(BY64:BY71)/SUM(BX72,BX75) -> 0.0029549821 | CA74: =CA72/CA90 -> 0.94918789 | CB74: Blended Cost of Deposits | CC74: =SUM(CB64:CB71)/SUM(CA72,CA75) -> 0.0028539424 | CD74: =CD72/CD90 -> 0.91254056 | CE74: Blended Cost of Deposits | CF74: =SUM(CE64:CE71)/SUM(CD72,CD75) -> 0.0028546681 | CH74: Time deposits | CI74: 5964017 | CJ74: 41960 | CK74: 0.007 | CL74: 6435102 | CM74: 52953 | CN74: 0.0082 | CO74: 7423695 | CP74: 80503 | CQ74: 0.0108 | CS74: Time deposits | CT74: 6851461 | CU74: 80888 | CV74: 0.0118 | CW74: 5037122 | CX74: 99065 | CY74: 0.0197
P75: =P57*(1+13.5%) -> 2238662.7 | AX75: Time deposits | AY75: 9473744 | AZ75: 106038 | BA75: 0.0112 | BB75: 8493511 | BC75: 33599 | BD75: 0.004 | BE75: 9465608 | BG75: 111411 | BH75: 0.0118 | BL75: Non Interest bearing deposits | BM75: 10502618 | BP75: 11089537 | BS75: 10627718 | BW75: Demand deposits | BX75: 9371481 | CA75: 7928460 | CD75: 6834871 | CH75: Interest Bearing Deposits | CI75: =SUM(CI71:CI74) -> 14215715 | CK75: =SUM(CJ71:CJ74)/CI75 -> 0.0044666061 | CL75: =SUM(CL71:CL74) -> 13645091 | CN75: =SUM(CM71:CM74)/CL75 -> 0.0055620736 | CO75: =SUM(CO71:CO74) -> 13752887 | CQ75: =SUM(CP71:CP74)/CO75 -> 0.0077881829 | CS75: Interest Bearing Deposits | CT75: =SUM(CT71:CT74) -> 12471879 | CV75: =SUM(CU71:CU74)/CT75 -> 0.009360017 | CW75: =SUM(CW71:CW74) -> 7978268 | CY75: =SUM(CX71:CX74)/CW75 -> 0.01622871
AX78: Interest Bearing Deposits | AY78: =SUM(AY71:AY75) -> 31515321 | AZ78: =SUM(AZ71:AZ75) -> 251838 | BA78: =AZ78/AY78 -> 0.0079909705 | BB78: =SUM(BB71:BB75) -> 30212286 | BC78: =SUM(BC71:BC75) -> 69159 | BD78: =BC78/BB78 -> 0.0022891019 | BE78: =SUM(BE71:BE75) -> 26939739 | BF78: =SUM(BF71:BF75) -> 0 | BG78: =SUM(BG71:BG75) -> 184742 | BH78: =BG78/BE78 -> 0.0068576017 | BL78: % of Deposits | BM78: =1-BM73 -> 0.29135844 | BP78: =1-BP73 -> 0.33371814 | BS78: =1-BS73 -> 0.34490153 | BW78: Federal funds purchased and other short-term borrowings | BX78: 25591 | BY78: 713 | BZ78: 0.0279 | CA78: 4797 | CB78: 58 | CC78: 0.0121 | CD78: 888 | CE78: 0 | CF78: 0 | CH78: % of Deposits | CI78: =CI75/SUM(CI75,CI82) -> 0.73294253 | CL78: =CL75/SUM(CL75,CL82) -> 0.77760329 | CO78: =CO75/SUM(CO75,CO82) -> 0.81664755 | CS78: % of Deposits | CT78: =CT75/SUM(CT75,CT82) -> 0.83756191 | CW78: =CW75/SUM(CW75,CW82) -> 0.84532216
AX81: % of Deposits | AY81: =AY78/SUM(AY78,AY84) -> 0.58039715 | BB81: =BB78/SUM(BB78,BB84) -> 0.58683211 | BE81: =BE78/SUM(BE78,BE84) -> 0.66088882 | BL81: Federal funds purchased and other short-term borrowings | BM81: 44881 | BN81: 1763 | BO81: 0.0393 | BP81: 32222 | BQ81: 1398 | BR81: 0.0434 | BS81: 34546 | BT81: 1003 | BU81: 0.029 | BW81: FHLB advances | BX81: 380868 | BY81: 5585 | BZ81: 0.0147 | CA81: 327080 | CB81: 4270 | CC81: 0.0131 | CD81: 349767 | CE81: 4116 | CF81: 0.0118 | CH81: % of IBLs | CI81: =CI75/CI93 -> 0.90583879 | CJ81: Blended Cost of Deposits | CK81: =SUM(CJ71:CJ74)/SUM(CI75,CI82) -> 0.0032737656 | CL81: =CL75/CL93 -> 0.89682229 | CM81: Blended Cost of Deposits | CN81: =SUM(CM71:CM74)/SUM(CL75,CL82) -> 0.0043250867 | CO81: =CO75/CO93 -> 0.87442876 | CP81: Blended Cost of Deposits | CQ81: =SUM(CP71:CP74)/SUM(CO75,CO82) -> 0.0063602005 | CS81: % of IBLs | CT81: =CT75/CT93 -> 0.82423658 | CU81: Blended Cost of Deposits | CV81: =SUM(CU71:CU74)/SUM(CT75,CT82) -> 0.0078395938 | CW81: =CW75/CW93 -> 0.75337475 | CX81: Blended Cost of Deposits | CY81: =CY75/CY93 -> 0.724496
AX82: % of IBLs | AY82: =AY78/AY96 -> 0.97501997 | BB82: =BB78/BB96 -> 0.97216075 | BE82: =BE78/BE96 -> 0.93546357 | BL82: FHLB advances | BM82: 592257 | BN82: 16697 | BO82: 0.0282 | BP82: 327435 | BQ82: 10447 | BR82: 0.0319 | BS82: 391480 | BT82: 7751 | BU82: 0.0198 | BW82: Repurchase agreements (1) | BX82: 211475 | BY82: 9304 | BZ82: 0.044 | CA82: 404096 | CB82: 20907 | CC82: 0.0517 | CD82: 955147 | CE82: 38395 | CF82: 0.0402 | CH82: Demand deposits | CI82: 5179687 | CL82: 3902534 | CO82: 3087777 | CS82: Demand deposits | CT82: 2418816 | CW82: 1459871
AX84: Non Interest bearing deposits | AY84: =AY100 -> 22784258 | AZ84: 0 | BA84: 0 | BB84: =BB100 -> 21271410 | BC84: 0 | BD84: 0 | BE84: =BE100 -> 13823152 | BG84: 0 | BH84: 0 | BL84: Repurchase agreements (1) | BM84: 74926 | BN84: 13582 | BO84: 0.1813 | BP84: 50000 | BQ84: 12110 | BR84: 0.2422 | BS84: 140000 | BT84: 9476 | BU84: 0.0677 | BW84: Short-term borrowing | BX84: =SUM(BX78:BX82) -> 617934 | BZ84: =SUM(BY78:BY82)/BX84 -> 0.025248651 | CA84: =SUM(CA78:CA82) -> 735973 | CC84: =SUM(CB78:CB82)/CA84 -> 0.034287943 | CD84: =SUM(CD78:CD82) -> 1305802 | CF84: =SUM(CE78:CE82)/CD84 -> 0.032555472 | CH84: Federal funds purchased and other borrowings | CI84: 155 | CJ84: 0 | CK84: 0 | CL84: 2975 | CM84: 4 | CN84: 0.0014 | CO84: 16684 | CP84: 458 | CQ84: 0.0275 | CS84: Federal funds purchased | CT84: 871 | CU84: 2 | CV84: 0.0023 | CW84: 2379 | CX84: 9 | CY84: 0.0037
AX85: % of Deposits | AY85: =1-AY81 -> 0.41960285 | AZ85: Blended Cost of Deposits | BA85: =AZ78/(SUM(AY78,AY84)) -> 0.0046379365 | BB85: =1-BB81 -> 0.41316789 | BC85: Blended Cost of Deposits | BD85: =BC78/(SUM(BB78,BB84)) -> 0.0013433185 | BE85: =1-BE81 -> 0.33911118 | BG85: Blended Cost of Deposits | BH85: =BG78/(SUM(BE78:BE84)) -> 0.0045321121 | BL85: Short-term borrowing | BM85: =SUM(BM81:BM84) -> 712064 | BO85: =SUM(BN81:BN84)/BM85 -> 0.044998764 | BP85: =SUM(BP81:BP84) -> 409657 | BR85: =SUM(BQ81:BQ84)/BP85 -> 0.058475749 | BS85: =SUM(BS81:BS84) -> 566026 | BU85: =SUM(BT81:BT84)/BS85 -> 0.032207001 | BW85: % of IBLs | BX85: =BX84/BX90 -> 0.030978151 | CA85: =CA84/CA90 -> 0.039186132 | CD85: =CD84/CD90 -> 0.073988821 | CH85: FHLB advances | CI85: 315867 | CJ85: 4173 | CK85: 0.0132 | CL85: 385644 | CM85: 6248 | CN85: 0.0162 | CO85: 679630 | CP85: 15461 | CQ85: 0.0227 | CS85: FHLB advances | CT85: 1324709 | CU85: 26641 | CV85: 0.0201 | CW85: 1333846 | CX85: 49940 | CY85: 0.0374
AX86: Federal funds purchased and other short-term borrowings | AY86: 81719 | AZ86: 1801 | BA86: 0.022 | BB86: 1584 | BC86: 42 | BD86: 0.0265 | BE86: 108398 | BG86: 1504 | BH86: 0.0139 | BL86: % of IBLs | BM86: =BM85/BM91 -> 0.026962969 | BP86: =BP85/BP91 -> 0.018038972 | BS86: =BS85/BS91 -> 0.027042518 | BW86: Long-term debt | BX86: 198589 | BY86: 5017 | BZ86: 0.0253 | CA86: 218353 | CB86: 4636 | CC86: 0.0212 | CD86: 237738 | CE86: 4823 | CF86: 0.0203 | CH86: Securities sold under repurchase agreements | CI86: 995000 | CJ86: 41381 | CK86: 0.0416 | CL86: 997938 | CM86: 46166 | CN86: 0.0463 | CO86: 1051844 | CP86: 48561 | CQ86: 0.0462 | CS86: Securities sold under repurchase agreements | CT86: 1047090 | CU86: 48993 | CV86: 0.0461 | CW86: 1027665 | CX86: 49725 | CY86: 0.0477
CS88: Other borrowings | CT88: 51312 | CU88: 2324 | CV88: 0.0447 | CW88: 12311 | CX88: 162 | CY88: 0.0132
AX89: FHLB advances | AY89: 105966 | AZ89: 1754 | BA89: 0.0166 | BB89: 404789 | BC89: 6881 | BD89: 0.017 | BE89: 664370 | BG89: 13792 | BH89: 0.0208 | BL89: Long-term borrowing | BM89: 152445 | BN89: 6643 | BO89: 0.0436 | BP89: 159185 | BQ89: 6488 | BR89: 0.0408 | BS89: 178882 | BT89: 5429 | BU89: 0.0303 | BW89: % of IBLs | BX89: =BX86/BX90 -> 0.0099556263 | CA89: =CA86/CA90 -> 0.011625983 | CD89: =CD86/CD90 -> 0.013470614 | CH89: Short-term borrowing | CI89: =SUM(CI84:CI86) -> 1311022 | CK89: =SUM(CJ84:CJ86)/CI89 -> 0.034746938 | CL89: =SUM(CL84:CL86) -> 1386557 | CN89: =SUM(CM84:CM86)/CL89 -> 0.037804432 | CO89: =SUM(CO84:CO86) -> 1748158 | CQ89: =SUM(CP84:CP86)/CO89 -> 0.036884538 | CS89: Short-term borrowing | CT89: =SUM(CT84:CT88) -> 2423982 | CV89: =SUM(CU84:CU88)/CT89 -> 0.032161955 | CW89: =SUM(CW84:CW88) -> 2376201 | CY89: =SUM(CX84:CX88)/CW89 -> 0.042014964
AX90: Repurchase agreements (1) | AY90: 467413 | AZ90: 14362 | BA90: 0.0307 | BB90: 306845 | BC90: 7999 | BD90: 0.0261 | BE90: 350849 | BG90: 11766 | BH90: 0.0335 | BL90: % of IBLs | BM90: =BM89/BM91 -> 0.0057724725 | BP90: =BP89/BP91 -> 0.0070096049 | BS90: =BS89/BS91 -> 0.0085462854 | BW90: Total interest-bearing liabilities | BX90: 19947414 | BY90: 104843 | BZ90: 0.0053 | CA90: 18781466 | CB90: 103376 | CC90: 0.0055 | CD90: 17648639 | CE90: 112820 | CF90: 0.0064 | CH90: % of IBLs | CI90: =CI89/CI93 -> 0.083539561 | CL90: =CL89/CL93 -> 0.091131325 | CO90: =CO89/CO93 -> 0.11115045 | CS90: % of IBLs | CT90: =CT89/CT93 -> 0.16019516 | CW90: =CW89/CW93 -> 0.22438076
AX91: Short-term borrowing | AY91: =SUM(AY86:AY90) -> 655098 | AZ91: Blended Cost of ST | BA91: =SUM(AZ86:AZ90)/AY91 -> 0.027350106 | BB91: =SUM(BB86:BB90) -> 713218 | BC91: Blended Cost of ST | BD91: =SUM(BC86:BC90)/BB91 -> 0.020922074 | BE91: =SUM(BE86:BE90) -> 1123617 | BG91: Blended Cost of ST | BH91: =SUM(BG86:BG90)/BE91 -> 0.024084719 | BL91: Total interest-bearing liabilities | BM91: 26408961 | BN91: 414487 | BO91: 0.0157 | BP91: 22709554 | BQ91: 265195 | BR91: 0.0117 | BS91: 20930965 | BT91: 140050 | BU91: 0.0067 | BW91: Noninterest-bearing liabilities and stockholders' equity: | CH91: Long-term debt | CI91: 166690 | CJ91: 3442 | CK91: 0.0206 | CL91: 183285 | CM91: 3855 | CN91: 0.021 | CO91: 226808 | CP91: 5832 | CQ91: 0.0257 | CS91: Long-term debt | CT91: 235570 | CU91: 6420 | CV91: 0.0269 | CW91: 235570 | CX91: 7816 | CY91: 0.0327
AW92: % of IBLs | AX92: =AY91/$AY$96 -> 0.020267401 | BA92: =$BB$91/BB96 -> 0.022949688 | BD92: =$BE$91/BE96 -> 0.039016813 | BK92: Noninterest-bearing liabilities and stockholders' equity: | CG92: % of IBLs | CH92: =CI91/CI93 -> 0.010621644 | CK92: =CL91/CL93 -> 0.012046389 | CN92: =CO91/CO93 -> 0.014420786 | CR92: % of IBLs | CS92: =CT91/CT93 -> 0.015568257 | CV92: =CW91/CW93 -> 0.022244488
AX93: Long-term borrowing | AY93: 152325 | AZ93: 5595 | BA93: 0.0367 | BB93: 151955 | BC93: 3082 | BD93: 0.0203 | BE93: 734921 | BF93: -7 | BG93: 6045 | BH93: 0.0082 | BP93: 11089537 | BS93: 10627718 | BW93: Accrued expenses and other liabilities | BX93: 544549 | CA93: 599436 | CD93: 451287 | CH93: Total interest-bearing liabilities | CI93: 15693427 | CJ93: 112492 | CK93: 0.0072 | CL93: 15214933 | CM93: 132168 | CN93: 0.0087 | CO93: 15727853 | CP93: 177422 | CQ93: 0.0113 | CS93: Total interest-bearing liabilities | CT93: 15131431 | CU93: 201117 | CV93: 0.0133 | CW93: 10590039 | CX93: 237129 | CY93: 0.0224
CW94: =SUM(CW89,CW91,CW75) -> 10590039 | CX94: =CW93-CW94 -> 0
AX95: % of IBLs | AY95: =AY93/AY96 -> 0.0047126259 | BA95: Cost of LT^ | BB95: =BB93/BB96 -> 0.0048895568 | BD95: Cost of LT^ | BE95: =BE93/BE96 -> 0.025519617 | BH95: Cost of LT^ | BL95: Accrued expenses and other liabilities | BM95: 812461 | BP95: 612656 | BS95: 541717 | BW95: Stockholders' equity | BX95: 3305929 | CA95: 3019095 | CD95: 2718173 | CH95: Noninterest-bearing liabilities: | CS95: Noninterest-bearing liabilities:
AX96: Total interest-bearing liabilities | AY96: 32322744 | AZ96: 275350 | BA96: 0.0085 | BB96: 31077459 | BC96: 87163 | BD96: 0.0028 | BE96: 28798277 | BG96: 217849 | BH96: 0.0076 | BL96: Stockholders' equity | BM96: 4760845 | BP96: 4130822 | BS96: 3687213 | BW96: Total liabilities and stockholders' equity | BX96: 33169373 | CA96: 30328457 | CD96: 27652970 | CH96: Demand deposits
AX99: Noninterest-bearing liabilities and stockholders' equity: | BL99: Total liabilities and stockholders' equity | BM99: 42484885 | BP99: 38542569 | BS99: 35787613 | CH99: Other liabilities | CI99: 343271 | CL99: 393948 | CO99: 523529 | CS99: Other liabilities | CT99: 282284 | CW99: 154138
AX100: Demand deposits | AY100: 22784258 | BB100: 21271410 | BE100: 13823152 | BL100: Interest rate spread | BO100: 0.031 | BR100: 0.0333 | BU100: 0.0322 | BW100: Interest rate spread | BZ100: 0.031 | CC100: 0.0316 | CF100: 0.0383 | CH100: Stockholders' equity | CI100: 2344307 | CL100: 2319128 | CO100: 2233962 | CS100: Stockholders' equity | CT100: 2345578 | CW100: 1634897
AX101: Accrued expenses and other liabilities | AY101: 1948255 | BB101: 1343010 | BE101: 1234178 | BL101: Net interest income and net interest margin | BN101: 1467813 | BO101: 0.0364 | BQ101: 1386508 | BR101: 0.0378 | BT101: 1185069 | BU101: 0.0348 | BW101: Net interest income and net interest margin | BY101: 1032638 | BZ101: 0.033 | CB101: 950439 | CC101: 0.0335 | CE101: 1040878 | CF101: 0.0403 | CH101: Total liabilities and stockholders' equity | CI101: 23560692 | CL101: 21830543 | CO101: 21573121 | CS101: Total liabilities and stockholders' equity | CT101: 20178109 | CW101: 13838945
AX102: Stockholders' equity | AY102: 5783025 | BB102: 5559212 | BE102: 5082186 | CH102: Interest rate spread | CK102: 0.0418 | CN102: 0.0443 | CQ102: 0.0444 | CS102: Interest rate spread | CV102: 0.0485 | CY102: 0.0336
AX105: Total liabilities and stockholders' equity | AY105: 62838282 | BB105: 59251091 | BE105: 48937793 | CH105: Net interest income and net interest margin | CJ105: 956193 | CK105: 0.0438 | CM105: 918927 | CN105: 0.0463 | CP105: 903026 | CQ105: 0.0466 | CS105: Net interest income and net interest margin | CU105: 894714 | CV105: 0.0505 | CX105: 486091 | CY105: 0.0376
AX106: Interest rate spread | BA106: 0.0306 | BD106: 0.026 | BH106: 0.0269
AX107: Net interest income and net interest margin | AZ107: 2045881 | BA107: 0.0345 | BC107: 1531571 | BD107: 0.0272 | BG107: 1377193 | BH107: 0.0298 | CS107: Source
AX108: Source
BA112: 10616 | BB112: 15029 | BC112: 19352
BA114: 37323 | BB114: 38985 | BC114: 45760
BC116: 16781 | BD116: 16493
AY117: 2009 | AZ117: 2010 | BA117: 2011 | BB117: 2012 | BC117: 2013 | BD117: 2014 | BE117: 2015 | BF117: 2016 | BG117: 2017 | BH117: 2018 | BI117: 2019 | BJ117: 2020 | BK117: 2021 | BL117: 2022
...

Sheet IEA Yield + IBL Cost Build
B2: East West Bancorp Net Income Build ($m) | C2: 2009 | D2: 2010 | E2: 2011 | F2: 2012 | G2: 2013 | H2: 2014 | I2: 2015 | J2: 2016 | K2: 2017 | L2: 2018 | M2: 2019 | N2: 2020 | O2: 2021 | P2: 2022 | Q2: 2023 | R2: 2024 | S2: 2025 | T2: 2026 | U2: 2027
B3: Average FFR | C3: 0.0016 | D3: 0.0018 | E3: 0.001 | F3: 0.0014 | G3: 0.0011 | H3: 0.0009 | I3: 0.0013 | J3: 0.004 | K3: 0.01 | L3: 0.0183 | M3: 0.0216 | N3: 0.0038 | O3: 0.0008 | P3: 0.0168 | Q3: 0.0508 | R3: 0.0488 | S3: 0.0418 | T3: 0.0338 | U3: 0.025
D4: =ROUND(((D3-C3)/C3),3) -> 0.125 | E4: =ROUND(((E3-D3)/D3),3) -> -0.444 | F4: =ROUND(((F3-E3)/E3),3) -> 0.4 | G4: =ROUND(((G3-F3)/F3),3) -> -0.214 | H4: =ROUND(((H3-G3)/G3),3) -> -0.182 | I4: =ROUND(((I3-H3)/H3),3) -> 0.444 | J4: =ROUND(((J3-I3)/I3),3) -> 2.077 | K4: =ROUND(((K3-J3)/J3),3) -> 1.5 | ... P4: =ROUND(((P3-O3)/O3),3) -> 20
B5: Cash and Cash with Banks Yield % | C5: ='Net Income Build'!C7 -> 0.0103 | D5: ='Net Income Build'!D7 -> 0.0116 | E5: ='Net Income Build'!E7 -> 0.0222 | F5: ='Net Income Build'!F7 -> 0.0153 | G5: ='Net Income Build'!G7 -> 0.0146 | H5: ='Net Income Build'!H7 -> 0.0158 | I5: ='Net Income Build'!I7 -> 0.0097 | J5: ='Net Income Build'!J7 -> 0.0078 | ... P5: ='Net Income Build'!P7 -> 0.0131
B6: Implied beta to FFR | D6: =ROUND(((D5-C5)/C5),3) -> 0.126 | E6: =ROUND(((E5-D5)/D5),3) -> 0.914 | F6: =ROUND(((F5-E5)/E5),3) -> -0.311 | G6: =ROUND(((G5-F5)/F5),3) -> -0.046 | H6: =ROUND(((H5-G5)/G5),3) -> 0.082 | I6: =ROUND(((I5-H5)/H5),3) -> -0.386 | J6: =ROUND(((J5-I5)/I5),3) -> -0.196 | K6: =ROUND(((K5-J5)/J5),3) -> 0.91 | ... P6: =ROUND(((P5-O5)/O5),3) -> 4.038
B7: Repo Yield | C7: ='Net Income Build'!C13 -> 0.0876 | D7: ='Net Income Build'!D13 -> 0.0264 | E7: ='Net Income Build'!E13 -> 0.0188 | F7: ='Net Income Build'!F13 -> 0.0161 | G7: ='Net Income Build'!G13 -> 0.0141 | H7: ='Net Income Build'!H13 -> 0.0152 | I7: ='Net Income Build'!I13 -> 0.0148 | J7: ='Net Income Build'!J13 -> 0.0179 | ... P7: ='Net Income Build'!P13 -> 0.0213
B8: Implied beta to FFR
B9: Loan Yield | C9: ='Net Income Build'!C19 -> 0.063594962 | D9: ='Net Income Build'!D19 -> 0.072842313 | E9: ='Net Income Build'!E19 -> 0.067376882 | F9: ='Net Income Build'!F19 -> 0.065346698 | G9: ='Net Income Build'!G19 -> 0.060174132 | H9: ='Net Income Build'!H19 -> 0.052 | I9: ='Net Income Build'!I19 -> 0.0435 | J9: ='Net Income Build'!J19 -> 0.0427 | ... P9: ='Net Income Build'!P19 -> 0.0452
B10: Implied Composite beta to FFR
B11: Securities Yield | E11: =E9 -> 0.067376882 | F11: =F9 -> 0.065346698 | G11: =G9 -> 0.060174132 | H11: =H9 -> 0.052 | I11: =I9 -> 0.0435 | J11: =J9 -> 0.0427 | K11: =K9 -> 0.044
B12: IB Deposit Cost
B13: Implied Composite beta to FFR
B14: LT Borrowing Cost
B15: Implied Composite beta to FFR
B16: ST Borrowing Cost
B17: Implied Composite beta to FFR

Sheet DCF
B2: East West Bancorp FCFE Build | C2: 2009 | D2: 2010 | E2: 2011 | F2: 2012 | G2: 2013 | H2: 2014 | I2: 2015 | J2: 2016 | K2: 2017 | L2: 2018 | M2: 2019 | N2: 2020 | O2: 2021 | P2: 2022 | Q2: 2023 | R2: 2024 | S2: 2025 | T2: 2026 | U2: 2027 | V2: Steady State
B3: Net Income (+) | C3: ='Net Income Build'!C72 -> 82441.816 | D3: ='Net Income Build'!D72 -> 164397.59 | E3: ='Net Income Build'!E72 -> 245289.72 | F3: ='Net Income Build'!F72 -> 281645.73 | G3: ='Net Income Build'!G72 -> 294966.43 | H3: ='Net Income Build'!H72 -> 345015.06 | I3: ='Net Income Build'!I72 -> 385104.75 | J3: ='Net Income Build'!J72 -> 432473.23 | ... U3: ='Net Income Build'!U72 -> 1254108.3 | V3: =U3*(1+0.02) -> 1279190.5
B4: Assets | C4: 13838945 | D4: =20178109 -> 20178109 | E4: =21573121 -> 21573121 | F4: =21830543 -> 21830543 | G4: 23560692 | H4: 27652970 | I4: 30328457 | J4: 33169373 | K4: 35787613 | L4: 38542569 | M4: 42484885 | N4: 48937793 | O4: 59251091 | P4: 62838282 | Q4: =Q5/Q6 -> 66910478 | R4: =R5/R6 -> 62791302 | S4: =S5/S6 -> 65930867 | T4: =T5/T6 -> 69227410 | U4: =U5/U6 -> 70958095 | V4: =V5/V6 -> 72377257
B5: IEAs | C5: =SUM('Net Income Build'!C5,'Net Income Build'!C11,'Net Income Build'!C17,'Net Income Build'!C23) -> 12910812 | D5: =SUM('Net Income Build'!D5,'Net Income Build'!D11,'Net Income Build'!D17,'Net Income Build'!D23) -> 17725514 | E5: =SUM('Net Income Build'!E5,'Net Income Build'!E11,'Net Income Build'!E17,'Net Income Build'!E23) -> 19393404 | F5: =SUM('Net Income Build'!F5,'Net Income Build'!F11,'Net Income Build'!F17,'Net Income Build'!F23) -> 19841180 | G5: =SUM('Net Income Build'!G5,'Net Income Build'!G11,'Net Income Build'!G17,'Net Income Build'!G23) -> 21827657 | H5: =SUM('Net Income Build'!H5,'Net Income Build'!H11,'Net Income Build'!H17,'Net Income Build'!H23) -> 25798578 | I5: =SUM('Net Income Build'!I5,'Net Income Build'!I11,'Net Income Build'!I17,'Net Income Build'!I23) -> 28390582 | J5: =SUM('Net Income Build'!J5,'Net Income Build'!J11,'Net Income Build'!J17,'Net Income Build'!J23) -> 31296775 | ... U5: =SUM('Net Income Build'!U5,'Net Income Build'!U11,'Net Income Build'!U17,'Net Income Build'!U23) -> 67410191 | V5: =U5*(1+0.02) -> 68758394
B6: % of total assets | C6: =C5/C4 -> 0.93293325 | D6: =D5/D4 -> 0.87845268 | E6: =E5/E4 -> 0.89896144 | F6: =F5/F4 -> 0.90887249 | G6: =G5/G4 -> 0.9264438 | H6: =H5/H4 -> 0.93294058 | I6: =I5/I4 -> 0.93610374 | J6: =J5/J4 -> 0.94354437 | ... P6: =P5/P4 -> 0.94383647 | Q6: 0.95 | R6: 0.95 | S6: 0.95 | T6: 0.95 | U6: 0.95 | V6: 0.95
B7: CET 1 Ratio | C7: 0.179 | D7: 0.157 | E7: 0.148 | F7: 0.148 | G7: 0.119 | H7: 0.11 | I7: 0.107 | J7: 0.109 | K7: 0.114 | L7: 0.122 | M7: 0.129 | N7: 0.127 | O7: 0.128 | P7: 0.127 | Q7: =P7+($U$7-$P$7)/10 -> 0.1273 | R7: =Q7+($U$7-$P$7)/5 -> 0.1279 | S7: =R7+($U$7-$P$7)/10 -> 0.1282 | T7: =S7+($U$7-$P$7)/10 -> 0.1285 | U7: 0.13 | V7: =U7 -> 0.13
B8: CET 1 Capital | C8: 2011158 | D8: 1865602 | E8: 2074963 | F8: 2116757 | G8: 2102476 | H8: 2405452 | I8: 2686627 | J8: 2976002 | K8: 3390070 | L8: 3966842 | M8: 4546592 | N8: 4882555 | O8: 5559357 | P8: 6347108 | Q8: =Q9*Q7 -> 6814163.1 | R8: =R9*R7 -> 6424806 | S8: =S9*S7 -> 6761869.7 | T8: =T9*T7 -> 7116577.8 | U8: =U9*U7 -> 7379641.9 | V8: =U8*(1+0.02) -> 7527234.8
B9: Implied RWAs | C9: =C8/C7 -> 11235520 | D9: =D8/D7 -> 11882815 | E9: =E8/E7 -> 14020020 | F9: =F8/F7 -> 14302412 | G9: =G8/G7 -> 17667866 | H9: =H8/H7 -> 21867745 | I9: =I8/I7 -> 25108664 | J9: =J8/J7 -> 27302771 | ... P9: =P8/P7 -> 49977228 | Q9: =Q10*Q4 -> 53528382 | R9: =R10*R4 -> 50233041 | S9: =S10*S4 -> 52744693 | T9: =T10*T4 -> 55381928 | U9: =U10*U4 -> 56766476 | V9: =V10*V4 -> 57901806
B10: Implied Risk Weighting % | C10: =C9/C4 -> 0.81187688 | D10: =D9/D4 -> 0.58889638 | E10: =E9/E4 -> 0.64988373 | F10: =F9/F4 -> 0.65515604 | G10: =G9/G4 -> 0.74988738 | H10: =H9/H4 -> 0.79079193 | I10: =I9/I4 -> 0.82789123 | J10: =J9/J4 -> 0.82313195 | ... P10: =P9/P4 -> 0.79533092 | Q10: 0.8 | R10: 0.8 | S10: 0.8 | T10: 0.8 | U10: 0.8 | V10: 0.8
B11: CET 1 YoY Delta (-) | D11: =D8-C8 -> -145556 | E11: =E8-D8 -> 209361 | F11: =F8-E8 -> 41794 | G11: =G8-F8 -> -14281 | H11: =H8-G8 -> 302976 | I11: =I8-H8 -> 281175 | J11: =J8-I8 -> 289375 | K11: =K8-J8 -> 414068 | ... V11: =V8-U8 -> 147592.84
B12: FCFE | C12: =C3-C11 -> 82441.816 | D12: =D3-D11 -> 309953.59 | E12: =E3-E11 -> 35928.721 | F12: =F3-F11 -> 239851.73 | G12: =G3-G11 -> 309247.43 | H12: =H3-H11 -> 42039.062 | I12: =I3-I11 -> 103929.75 | J12: =J3-J11 -> 143098.23 | ... V12: =V3-V11 -> 1131597.6
B13: NPV of Stage 1 FCFE | Q13: =Q12/Q15 -> 607513.55 | R13: =R12/R15 -> 1254857.8 | S13: =S12/S15 -> 638520.99 | T13: =T12/T15 -> 655031.43 | U13: =U12/U15 -> 703606.55
Q14: 0.5 | R14: =Q14+1 -> 1.5 | S14: =R14+1 -> 2.5 | T14: =S14+1 -> 3.5 | U14: =T14+1 -> 4.5
Q15: =(1+$D$23)^Q14 -> 1.0387935 | R15: =(1+$D$23)^R14 -> 1.1209538 | S15: =(1+$D$23)^S14 -> 1.2096123 | T15: =(1+$D$23)^T14 -> 1.3052829 | U15: =(1+$D$23)^U14 -> 1.4085204
B16: Discount Rate | P16: Implied ROE | Q16: =Q3/Q17 -> 0.16206129 | R16: =R3/R17 -> 0.15928113 | S16: =S3/S17 -> 0.16500087 | T16: =T3/T17 -> 0.17089985 | U16: =U3/U17 -> 0.17082374 | V16: =(V12/(D23-0.02))/U15 -> 13595657
B17: Tax Rate | D17: 0.23 | P17: 6309000 | Q17: =P17+Q11 -> 6776055.1 | R17: =Q17+R11 -> 6386698 | S17: =R17+S11 -> 6723761.7 | T17: =S17+T11 -> 7078469.8 | U17: =T17+U11 -> 7341533.9
B19: Risk Free Rate | D19: 0.0423 | S19: =U3*15.2 -> 19062446
B20: Un-levered Beta | D20: 0.84 | S20: =(S19/7600000)^(1/5) -1 -> 0.20191293
B21: ERP | D21: 0.0438
F22: =F11/F3 -> 0.1483921 | G22: =G11/G3 -> -0.048415678 | H22: =H11/H3 -> 0.87815297 | I22: =I11/I3 -> 0.73012602 | J22: =J11/J3 -> 0.66911656 | K22: =K11/K3 -> 0.81779376 | L22: =L11/L3 -> 0.82093864 | M22: =M11/M3 -> 0.85839151 | ... P22: =P11/P3 -> 0.69830383
B23: Cost of Equity | D23: =SUM(D19,(D20*D21)) -> 0.079092 | L23: =AVERAGE(F22:P22) -> 0.63078842
B25: Perpetuity Growth Method
B26: Growth Rate | D26: 0.02
B27: Stage 2 FCF | D27: =U12*(1+D26)/(D23-D26) -> 17106631
B28: Cumulative PV of Stage 1 FCF | D28: =SUM(Q13:U13) -> 3859530.3
B29: PV of Stage 2 FCF | D29: =D27/U15 -> 12145107
B30: Equity Value | D30: =SUM(D28:D29) -> 16004638
B31: Diluted Shares Outstanding | D31: 141876
B32: Intrinsic Stock Price | D32: =D30/D31 -> 112.80722
B33: Current Stock Price | D33: 56.99
B34: Margin of Safety | D34: =D32/D33-1 -> 0.97942136
B35: Implied IRR | D35: =((D30*(1+D23)^5)/(D33*D31))^(1/5) -1 -> 0.23698981
B36: Implied Terminal Multiple ('27 Earnings) | D36: =D30/'Net Income Build'!U72 -> 12.761767
